{
  "season": 2020,
  "source": "api.formula-e.pulselive.com",
  "completedRounds": 11,
  "totalRounds": 11,
  "calendar": [
    {
      "round": 1,
      "key": "diriyah",
      "name": "Diriyah",
      "country": "SA",
      "kind": "street",
      "city": "Diriyah",
      "date": "2019-11-22",
      "completed": true,
      "raceId": "f825a693-f18b-4d2e-8e8b-293a01f5e517"
    },
    {
      "round": 2,
      "key": "diriyah",
      "name": "Diriyah",
      "country": "SA",
      "kind": "street",
      "city": "Diriyah",
      "date": "2019-11-23",
      "completed": true,
      "raceId": "7d35179d-7797-4080-8799-3129a1cb0e80"
    },
    {
      "round": 3,
      "key": "santiago",
      "name": "Santiago",
      "country": "CL",
      "kind": "street",
      "city": "Santiago",
      "date": "2020-01-18",
      "completed": true,
      "raceId": "c6bc6351-8c48-4a2d-8160-c29f145f90da"
    },
    {
      "round": 4,
      "key": "mexico-city",
      "name": "Mexico City",
      "country": "MX",
      "kind": "circuit",
      "city": "Mexico City",
      "date": "2020-02-15",
      "completed": true,
      "raceId": "5259bb2b-0d65-4cae-ae0d-b047cc910252"
    },
    {
      "round": 5,
      "key": "marrakesh",
      "name": "Marrakesh",
      "country": "MA",
      "kind": "circuit",
      "city": "Marrakesh",
      "date": "2020-02-29",
      "completed": true,
      "raceId": "71726c0e-453c-456b-8b38-3e3c04ae2ba2"
    },
    {
      "round": 6,
      "key": "berlin",
      "name": "Berlin",
      "country": "DE",
      "kind": "circuit",
      "city": "Berlin",
      "date": "2020-08-05",
      "completed": true,
      "raceId": "7f2e4fae-4d11-4bbe-811d-5e190bbcab3f"
    },
    {
      "round": 7,
      "key": "berlin",
      "name": "Berlin",
      "country": "DE",
      "kind": "circuit",
      "city": "Berlin",
      "date": "2020-08-06",
      "completed": true,
      "raceId": "3c6847e1-6e8f-43a1-b1d6-38e4d8126f8a"
    },
    {
      "round": 8,
      "key": "berlin",
      "name": "Berlin",
      "country": "DE",
      "kind": "circuit",
      "city": "Berlin",
      "date": "2020-08-08",
      "completed": true,
      "raceId": "92b4e8b0-4192-403e-ae87-00c7e7c34511"
    },
    {
      "round": 9,
      "key": "berlin",
      "name": "Berlin",
      "country": "DE",
      "kind": "circuit",
      "city": "Berlin",
      "date": "2020-08-09",
      "completed": true,
      "raceId": "c54d37fb-9b6a-411b-a8e1-7e1135cf8e6d"
    },
    {
      "round": 10,
      "key": "berlin",
      "name": "Berlin",
      "country": "DE",
      "kind": "circuit",
      "city": "Berlin",
      "date": "2020-08-12",
      "completed": true,
      "raceId": "f44c8356-840d-42cc-9045-6ec79380b062"
    },
    {
      "round": 11,
      "key": "berlin",
      "name": "Berlin",
      "country": "DE",
      "kind": "circuit",
      "city": "Berlin",
      "date": "2020-08-13",
      "completed": true,
      "raceId": "97b4c0d9-1f03-484e-a3c6-7e9365d1d895"
    }
  ],
  "results": {
    "1": {
      "race": [
        {
          "position": 1,
          "code": "BIR",
          "name": "Sam Bird",
          "team": "ENVISION VIRGIN RACING",
          "grid": 5,
          "status": "Finished",
          "points": 26.0,
          "pole": false,
          "fastestLap": false
        },
        {
          "position": 2,
          "code": "LOT",
          "name": "André Lotterer",
          "team": "TAG HEUER PORSCHE FORMULA E TEAM",
          "grid": 7,
          "status": "Finished",
          "points": 18.0,
          "pole": false,
          "fastestLap": false
        },
        {
          "position": 3,
          "code": "VAN",
          "name": "Stoffel Vandoorne",
          "team": "MERCEDES-BENZ EQ FORMULA E TEAM",
          "grid": 2,
          "status": "Finished",
          "points": 15.0,
          "pole": false,
          "fastestLap": false
        },
        {
          "position": 4,
          "code": "ROW",
          "name": "Oliver Rowland",
          "team": "NISSAN E.DAMS",
          "grid": 8,
          "status": "Finished",
          "points": 12.0,
          "pole": false,
          "fastestLap": false
        },
        {
          "position": 5,
          "code": "FRI",
          "name": "Robin Frijns",
          "team": "ENVISION VIRGIN RACING",
          "grid": 12,
          "status": "Finished",
          "points": 10.0,
          "pole": false,
          "fastestLap": false
        },
        {
          "position": 6,
          "code": "DEV",
          "name": "Nyck De Vries",
          "team": "MERCEDES-BENZ EQ FORMULA E TEAM",
          "grid": 3,
          "status": "Finished",
          "points": 8.0,
          "pole": false,
          "fastestLap": false
        },
        {
          "position": 7,
          "code": "MOR",
          "name": "Edoardo Mortara",
          "team": "ROKIT VENTURI RACING",
          "grid": 4,
          "status": "Finished",
          "points": 6.0,
          "pole": false,
          "fastestLap": false
        },
        {
          "position": 8,
          "code": "SIM",
          "name": "Alexander Sims",
          "team": "BMW I ANDRETTI MOTORSPORT",
          "grid": 1,
          "status": "Finished",
          "points": 7.0,
          "pole": true,
          "fastestLap": false
        },
        {
          "position": 9,
          "code": "DAM",
          "name": "Jérôme D'Ambrosio",
          "team": "Mahindra Racing",
          "grid": 6,
          "status": "Finished",
          "points": 2.0,
          "pole": false,
          "fastestLap": false
        },
        {
          "position": 10,
          "code": "EVA",
          "name": "Mitch Evans",
          "team": "PANASONIC JAGUAR RACING",
          "grid": 16,
          "status": "Finished",
          "points": 2.0,
          "pole": false,
          "fastestLap": true
        },
        {
          "position": 11,
          "code": "WEH",
          "name": "Pascal Wehrlein",
          "team": "Mahindra Racing",
          "grid": 13,
          "status": "Finished",
          "points": 0.0,
          "pole": false,
          "fastestLap": false
        },
        {
          "position": 12,
          "code": "MAS",
          "name": "Felipe Massa",
          "team": "ROKIT VENTURI RACING",
          "grid": 17,
          "status": "Finished",
          "points": 0.0,
          "pole": false,
          "fastestLap": false
        },
        {
          "position": 13,
          "code": "DIG",
          "name": "Lucas Di Grassi",
          "team": "AUDI SPORT ABT SCHAEFFLER",
          "grid": 19,
          "status": "Finished",
          "points": 0.0,
          "pole": false,
          "fastestLap": false
        },
        {
          "position": 14,
          "code": "DAC",
          "name": "António Félix Da Costa",
          "team": "DS TECHEETAH",
          "grid": 21,
          "status": "Finished",
          "points": 0.0,
          "pole": false,
          "fastestLap": false
        },
        {
          "position": 15,
          "code": "TUR",
          "name": "Oliver Turvey",
          "team": "NIO 333 FE TEAM",
          "grid": 10,
          "status": "Finished",
          "points": 0.0,
          "pole": false,
          "fastestLap": false
        },
        {
          "position": 16,
          "code": "CAL",
          "name": "James Calado",
          "team": "PANASONIC JAGUAR RACING",
          "grid": 24,
          "status": "Finished",
          "points": 0.0,
          "pole": false,
          "fastestLap": false
        },
        {
          "position": 17,
          "code": "JAN",
          "name": "Neel Jani",
          "team": "TAG HEUER PORSCHE FORMULA E TEAM",
          "grid": 20,
          "status": "Finished",
          "points": 0.0,
          "pole": false,
          "fastestLap": false
        },
        {
          "position": 18,
          "code": "GUE",
          "name": "Maximilian Günther",
          "team": "BMW I ANDRETTI MOTORSPORT",
          "grid": 9,
          "status": "Finished",
          "points": 0.0,
          "pole": false,
          "fastestLap": false
        },
        {
          "position": 19,
          "code": "HAR",
          "name": "Brendon Hartley",
          "team": "GEOX DRAGON",
          "grid": 18,
          "status": "Finished",
          "points": 0.0,
          "pole": false,
          "fastestLap": false
        },
        {
          "position": 20,
          "code": "QMA",
          "name": "Qinghua Ma",
          "team": "NIO 333 FE TEAM",
          "grid": 22,
          "status": "Finished",
          "points": 0.0,
          "pole": false,
          "fastestLap": false
        },
        {
          "position": null,
          "code": "JEV",
          "name": "Jean-Éric Vergne",
          "team": "DS TECHEETAH",
          "grid": 11,
          "status": "DNF",
          "points": 0.0,
          "pole": false,
          "fastestLap": false
        },
        {
          "position": null,
          "code": "ABT",
          "name": "Daniel Abt",
          "team": "AUDI SPORT ABT SCHAEFFLER",
          "grid": 15,
          "status": "DNF",
          "points": 0.0,
          "pole": false,
          "fastestLap": false
        },
        {
          "position": null,
          "code": "BUE",
          "name": "Sébastien Buemi",
          "team": "NISSAN E.DAMS",
          "grid": 14,
          "status": "DNF",
          "points": 0.0,
          "pole": false,
          "fastestLap": false
        },
        {
          "position": null,
          "code": "MUE",
          "name": "Nico Müller",
          "team": "GEOX DRAGON",
          "grid": 23,
          "status": "DNS",
          "points": 0.0,
          "pole": false,
          "fastestLap": false
        }
      ],
      "raceId": "f825a693-f18b-4d2e-8e8b-293a01f5e517"
    },
    "2": {
      "race": [
        {
          "position": 1,
          "code": "SIM",
          "name": "Alexander Sims",
          "team": "BMW I ANDRETTI MOTORSPORT",
          "grid": 1,
          "status": "Finished",
          "points": 28.0,
          "pole": true,
          "fastestLap": false
        },
        {
          "position": 2,
          "code": "DIG",
          "name": "Lucas Di Grassi",
          "team": "AUDI SPORT ABT SCHAEFFLER",
          "grid": 3,
          "status": "Finished",
          "points": 18.0,
          "pole": false,
          "fastestLap": false
        },
        {
          "position": 3,
          "code": "VAN",
          "name": "Stoffel Vandoorne",
          "team": "MERCEDES-BENZ EQ FORMULA E TEAM",
          "grid": 11,
          "status": "Finished",
          "points": 15.0,
          "pole": false,
          "fastestLap": false
        },
        {
          "position": 4,
          "code": "MOR",
          "name": "Edoardo Mortara",
          "team": "ROKIT VENTURI RACING",
          "grid": 8,
          "status": "Finished",
          "points": 12.0,
          "pole": false,
          "fastestLap": false
        },
        {
          "position": 5,
          "code": "ROW",
          "name": "Oliver Rowland",
          "team": "NISSAN E.DAMS",
          "grid": 16,
          "status": "Finished",
          "points": 10.0,
          "pole": false,
          "fastestLap": false
        },
        {
          "position": 6,
          "code": "ABT",
          "name": "Daniel Abt",
          "team": "AUDI SPORT ABT SCHAEFFLER",
          "grid": 14,
          "status": "Finished",
          "points": 8.0,
          "pole": false,
          "fastestLap": false
        },
        {
          "position": 7,
          "code": "CAL",
          "name": "James Calado",
          "team": "PANASONIC JAGUAR RACING",
          "grid": 21,
          "status": "Finished",
          "points": 6.0,
          "pole": false,
          "fastestLap": false
        },
        {
          "position": 8,
          "code": "JEV",
          "name": "Jean-Éric Vergne",
          "team": "DS TECHEETAH",
          "grid": 24,
          "status": "Finished",
          "points": 4.0,
          "pole": false,
          "fastestLap": false
        },
        {
          "position": 9,
          "code": "HAR",
          "name": "Brendon Hartley",
          "team": "GEOX DRAGON",
          "grid": 19,
          "status": "Finished",
          "points": 2.0,
          "pole": false,
          "fastestLap": false
        },
        {
          "position": 10,
          "code": "DAC",
          "name": "António Félix Da Costa",
          "team": "DS TECHEETAH",
          "grid": 5,
          "status": "Finished",
          "points": 3.0,
          "pole": false,
          "fastestLap": true
        },
        {
          "position": 11,
          "code": "GUE",
          "name": "Maximilian Günther",
          "team": "BMW I ANDRETTI MOTORSPORT",
          "grid": 9,
          "status": "Finished",
          "points": 0.0,
          "pole": false,
          "fastestLap": false
        },
        {
          "position": 12,
          "code": "BUE",
          "name": "Sébastien Buemi",
          "team": "NISSAN E.DAMS",
          "grid": 2,
          "status": "Finished",
          "points": 0.0,
          "pole": false,
          "fastestLap": false
        },
        {
          "position": 13,
          "code": "JAN",
          "name": "Neel Jani",
          "team": "TAG HEUER PORSCHE FORMULA E TEAM",
          "grid": 18,
          "status": "Finished",
          "points": 0.0,
          "pole": false,
          "fastestLap": false
        },
        {
          "position": 14,
          "code": "LOT",
          "name": "André Lotterer",
          "team": "TAG HEUER PORSCHE FORMULA E TEAM",
          "grid": 10,
          "status": "Finished",
          "points": 0.0,
          "pole": false,
          "fastestLap": false
        },
        {
          "position": 15,
          "code": "WEH",
          "name": "Pascal Wehrlein",
          "team": "Mahindra Racing",
          "grid": 13,
          "status": "Finished",
          "points": 0.0,
          "pole": false,
          "fastestLap": false
        },
        {
          "position": 16,
          "code": "DEV",
          "name": "Nyck De Vries",
          "team": "MERCEDES-BENZ EQ FORMULA E TEAM",
          "grid": 23,
          "status": "Finished",
          "points": 0.0,
          "pole": false,
          "fastestLap": false
        },
        {
          "position": 17,
          "code": "MAS",
          "name": "Felipe Massa",
          "team": "ROKIT VENTURI RACING",
          "grid": 15,
          "status": "Finished",
          "points": 0.0,
          "pole": false,
          "fastestLap": false
        },
        {
          "position": 18,
          "code": "EVA",
          "name": "Mitch Evans",
          "team": "PANASONIC JAGUAR RACING",
          "grid": 6,
          "status": "Finished",
          "points": 0.0,
          "pole": false,
          "fastestLap": false
        },
        {
          "position": 19,
          "code": "QMA",
          "name": "Qinghua Ma",
          "team": "NIO 333 FE TEAM",
          "grid": 20,
          "status": "Finished",
          "points": 0.0,
          "pole": false,
          "fastestLap": false
        },
        {
          "position": null,
          "code": "DAM",
          "name": "Jérôme D'Ambrosio",
          "team": "Mahindra Racing",
          "grid": 4,
          "status": "Finished",
          "points": 0.0,
          "pole": false,
          "fastestLap": false
        },
        {
          "position": null,
          "code": "TUR",
          "name": "Oliver Turvey",
          "team": "NIO 333 FE TEAM",
          "grid": 17,
          "status": "DSQ",
          "points": 0.0,
          "pole": false,
          "fastestLap": false
        },
        {
          "position": null,
          "code": "FRI",
          "name": "Robin Frijns",
          "team": "ENVISION VIRGIN RACING",
          "grid": 12,
          "status": "DNF",
          "points": 0.0,
          "pole": false,
          "fastestLap": false
        },
        {
          "position": null,
          "code": "MUE",
          "name": "Nico Müller",
          "team": "GEOX DRAGON",
          "grid": 22,
          "status": "DNF",
          "points": 0.0,
          "pole": false,
          "fastestLap": false
        },
        {
          "position": null,
          "code": "BIR",
          "name": "Sam Bird",
          "team": "ENVISION VIRGIN RACING",
          "grid": 7,
          "status": "DNF",
          "points": 0.0,
          "pole": false,
          "fastestLap": false
        }
      ],
      "raceId": "7d35179d-7797-4080-8799-3129a1cb0e80"
    },
    "3": {
      "race": [
        {
          "position": 1,
          "code": "GUE",
          "name": "Maximilian Günther",
          "team": "BMW I ANDRETTI MOTORSPORT",
          "grid": 2,
          "status": "Finished",
          "points": 25.0,
          "pole": false,
          "fastestLap": false
        },
        {
          "position": 2,
          "code": "DAC",
          "name": "António Félix Da Costa",
          "team": "DS TECHEETAH",
          "grid": 10,
          "status": "Finished",
          "points": 18.0,
          "pole": false,
          "fastestLap": false
        },
        {
          "position": 3,
          "code": "EVA",
          "name": "Mitch Evans",
          "team": "PANASONIC JAGUAR RACING",
          "grid": 1,
          "status": "Finished",
          "points": 19.0,
          "pole": true,
          "fastestLap": false
        },
        {
          "position": 4,
          "code": "WEH",
          "name": "Pascal Wehrlein",
          "team": "Mahindra Racing",
          "grid": 3,
          "status": "Finished",
          "points": 12.0,
          "pole": false,
          "fastestLap": false
        },
        {
          "position": 5,
          "code": "DEV",
          "name": "Nyck De Vries",
          "team": "MERCEDES-BENZ EQ FORMULA E TEAM",
          "grid": 8,
          "status": "Finished",
          "points": 10.0,
          "pole": false,
          "fastestLap": false
        },
        {
          "position": 6,
          "code": "VAN",
          "name": "Stoffel Vandoorne",
          "team": "MERCEDES-BENZ EQ FORMULA E TEAM",
          "grid": 9,
          "status": "Finished",
          "points": 8.0,
          "pole": false,
          "fastestLap": false
        },
        {
          "position": 7,
          "code": "DIG",
          "name": "Lucas Di Grassi",
          "team": "AUDI SPORT ABT SCHAEFFLER",
          "grid": 22,
          "status": "Finished",
          "points": 6.0,
          "pole": false,
          "fastestLap": false
        },
        {
          "position": 8,
          "code": "CAL",
          "name": "James Calado",
          "team": "PANASONIC JAGUAR RACING",
          "grid": 18,
          "status": "Finished",
          "points": 4.0,
          "pole": false,
          "fastestLap": false
        },
        {
          "position": 9,
          "code": "MAS",
          "name": "Felipe Massa",
          "team": "ROKIT VENTURI RACING",
          "grid": 4,
          "status": "Finished",
          "points": 2.0,
          "pole": false,
          "fastestLap": false
        },
        {
          "position": 10,
          "code": "BIR",
          "name": "Sam Bird",
          "team": "ENVISION VIRGIN RACING",
          "grid": 16,
          "status": "Finished",
          "points": 2.0,
          "pole": false,
          "fastestLap": true
        },
        {
          "position": 11,
          "code": "TUR",
          "name": "Oliver Turvey",
          "team": "NIO 333 FE TEAM",
          "grid": 5,
          "status": "Finished",
          "points": 0.0,
          "pole": false,
          "fastestLap": false
        },
        {
          "position": 12,
          "code": "MUE",
          "name": "Nico Müller",
          "team": "GEOX DRAGON",
          "grid": 19,
          "status": "Finished",
          "points": 0.0,
          "pole": false,
          "fastestLap": false
        },
        {
          "position": 13,
          "code": "BUE",
          "name": "Sébastien Buemi",
          "team": "NISSAN E.DAMS",
          "grid": 6,
          "status": "Finished",
          "points": 0.0,
          "pole": false,
          "fastestLap": false
        },
        {
          "position": 14,
          "code": "ABT",
          "name": "Daniel Abt",
          "team": "AUDI SPORT ABT SCHAEFFLER",
          "grid": 13,
          "status": "Finished",
          "points": 0.0,
          "pole": false,
          "fastestLap": false
        },
        {
          "position": 15,
          "code": "FRI",
          "name": "Robin Frijns",
          "team": "ENVISION VIRGIN RACING",
          "grid": 21,
          "status": "Finished",
          "points": 0.0,
          "pole": false,
          "fastestLap": false
        },
        {
          "position": 16,
          "code": "QMA",
          "name": "Qinghua Ma",
          "team": "NIO 333 FE TEAM",
          "grid": 24,
          "status": "Finished",
          "points": 0.0,
          "pole": false,
          "fastestLap": false
        },
        {
          "position": 17,
          "code": "ROW",
          "name": "Oliver Rowland",
          "team": "NISSAN E.DAMS",
          "grid": 23,
          "status": "Finished",
          "points": 0.0,
          "pole": false,
          "fastestLap": false
        },
        {
          "position": null,
          "code": "HAR",
          "name": "Brendon Hartley",
          "team": "GEOX DRAGON",
          "grid": 17,
          "status": "DNF",
          "points": 0.0,
          "pole": false,
          "fastestLap": false
        },
        {
          "position": null,
          "code": "DAM",
          "name": "Jérôme D'Ambrosio",
          "team": "Mahindra Racing",
          "grid": 20,
          "status": "Finished",
          "points": 0.0,
          "pole": false,
          "fastestLap": false
        },
        {
          "position": null,
          "code": "JEV",
          "name": "Jean-Éric Vergne",
          "team": "DS TECHEETAH",
          "grid": 11,
          "status": "DNF",
          "points": 0.0,
          "pole": false,
          "fastestLap": false
        },
        {
          "position": null,
          "code": "JAN",
          "name": "Neel Jani",
          "team": "TAG HEUER PORSCHE FORMULA E TEAM",
          "grid": 12,
          "status": "DNF",
          "points": 0.0,
          "pole": false,
          "fastestLap": false
        },
        {
          "position": null,
          "code": "MOR",
          "name": "Edoardo Mortara",
          "team": "ROKIT VENTURI RACING",
          "grid": 7,
          "status": "DNF",
          "points": 0.0,
          "pole": false,
          "fastestLap": false
        },
        {
          "position": null,
          "code": "LOT",
          "name": "André Lotterer",
          "team": "TAG HEUER PORSCHE FORMULA E TEAM",
          "grid": 14,
          "status": "DSQ",
          "points": 0.0,
          "pole": false,
          "fastestLap": false
        },
        {
          "position": null,
          "code": "SIM",
          "name": "Alexander Sims",
          "team": "BMW I ANDRETTI MOTORSPORT",
          "grid": 15,
          "status": "DNF",
          "points": 0.0,
          "pole": false,
          "fastestLap": false
        }
      ],
      "raceId": "c6bc6351-8c48-4a2d-8160-c29f145f90da"
    },
    "4": {
      "race": [
        {
          "position": 1,
          "code": "EVA",
          "name": "Mitch Evans",
          "team": "PANASONIC JAGUAR RACING",
          "grid": 2,
          "status": "Finished",
          "points": 26.0,
          "pole": false,
          "fastestLap": false
        },
        {
          "position": 2,
          "code": "DAC",
          "name": "António Félix Da Costa",
          "team": "DS TECHEETAH",
          "grid": 9,
          "status": "Finished",
          "points": 18.0,
          "pole": false,
          "fastestLap": false
        },
        {
          "position": 3,
          "code": "BUE",
          "name": "Sébastien Buemi",
          "team": "NISSAN E.DAMS",
          "grid": 4,
          "status": "Finished",
          "points": 15.0,
          "pole": false,
          "fastestLap": false
        },
        {
          "position": 4,
          "code": "JEV",
          "name": "Jean-Éric Vergne",
          "team": "DS TECHEETAH",
          "grid": 8,
          "status": "Finished",
          "points": 12.0,
          "pole": false,
          "fastestLap": false
        },
        {
          "position": 5,
          "code": "SIM",
          "name": "Alexander Sims",
          "team": "BMW I ANDRETTI MOTORSPORT",
          "grid": 18,
          "status": "Finished",
          "points": 11.0,
          "pole": false,
          "fastestLap": true
        },
        {
          "position": 6,
          "code": "DIG",
          "name": "Lucas Di Grassi",
          "team": "AUDI SPORT ABT SCHAEFFLER",
          "grid": 15,
          "status": "Finished",
          "points": 8.0,
          "pole": false,
          "fastestLap": false
        },
        {
          "position": 7,
          "code": "ROW",
          "name": "Oliver Rowland",
          "team": "NISSAN E.DAMS",
          "grid": 12,
          "status": "Finished",
          "points": 6.0,
          "pole": false,
          "fastestLap": false
        },
        {
          "position": 8,
          "code": "MOR",
          "name": "Edoardo Mortara",
          "team": "ROKIT VENTURI RACING",
          "grid": 11,
          "status": "Finished",
          "points": 4.0,
          "pole": false,
          "fastestLap": false
        },
        {
          "position": 9,
          "code": "WEH",
          "name": "Pascal Wehrlein",
          "team": "Mahindra Racing",
          "grid": 24,
          "status": "Finished",
          "points": 2.0,
          "pole": false,
          "fastestLap": false
        },
        {
          "position": 10,
          "code": "DAM",
          "name": "Jérôme D'Ambrosio",
          "team": "Mahindra Racing",
          "grid": 23,
          "status": "Finished",
          "points": 1.0,
          "pole": false,
          "fastestLap": false
        },
        {
          "position": 11,
          "code": "GUE",
          "name": "Maximilian Günther",
          "team": "BMW I ANDRETTI MOTORSPORT",
          "grid": 16,
          "status": "Finished",
          "points": 0.0,
          "pole": false,
          "fastestLap": false
        },
        {
          "position": 12,
          "code": "HAR",
          "name": "Brendon Hartley",
          "team": "GEOX DRAGON",
          "grid": 13,
          "status": "Finished",
          "points": 0.0,
          "pole": false,
          "fastestLap": false
        },
        {
          "position": 13,
          "code": "TUR",
          "name": "Oliver Turvey",
          "team": "NIO 333 FE TEAM",
          "grid": 21,
          "status": "Finished",
          "points": 0.0,
          "pole": false,
          "fastestLap": false
        },
        {
          "position": 14,
          "code": "JAN",
          "name": "Neel Jani",
          "team": "TAG HEUER PORSCHE FORMULA E TEAM",
          "grid": 14,
          "status": "Finished",
          "points": 0.0,
          "pole": false,
          "fastestLap": false
        },
        {
          "position": null,
          "code": "MAS",
          "name": "Felipe Massa",
          "team": "ROKIT VENTURI RACING",
          "grid": 19,
          "status": "DNF",
          "points": 0.0,
          "pole": false,
          "fastestLap": false
        },
        {
          "position": null,
          "code": "QMA",
          "name": "Qinghua Ma",
          "team": "NIO 333 FE TEAM",
          "grid": 20,
          "status": "DNF",
          "points": 0.0,
          "pole": false,
          "fastestLap": false
        },
        {
          "position": null,
          "code": "VAN",
          "name": "Stoffel Vandoorne",
          "team": "MERCEDES-BENZ EQ FORMULA E TEAM",
          "grid": 10,
          "status": "Finished",
          "points": 0.0,
          "pole": false,
          "fastestLap": false
        },
        {
          "position": null,
          "code": "DEV",
          "name": "Nyck De Vries",
          "team": "MERCEDES-BENZ EQ FORMULA E TEAM",
          "grid": 3,
          "status": "DNF",
          "points": 0.0,
          "pole": false,
          "fastestLap": false
        },
        {
          "position": null,
          "code": "FRI",
          "name": "Robin Frijns",
          "team": "ENVISION VIRGIN RACING",
          "grid": 6,
          "status": "DSQ",
          "points": 0.0,
          "pole": false,
          "fastestLap": false
        },
        {
          "position": null,
          "code": "ABT",
          "name": "Daniel Abt",
          "team": "AUDI SPORT ABT SCHAEFFLER",
          "grid": 22,
          "status": "DNF",
          "points": 0.0,
          "pole": false,
          "fastestLap": false
        },
        {
          "position": null,
          "code": "MUE",
          "name": "Nico Müller",
          "team": "GEOX DRAGON",
          "grid": 7,
          "status": "DNF",
          "points": 0.0,
          "pole": false,
          "fastestLap": false
        },
        {
          "position": null,
          "code": "BIR",
          "name": "Sam Bird",
          "team": "ENVISION VIRGIN RACING",
          "grid": 5,
          "status": "DNF",
          "points": 0.0,
          "pole": false,
          "fastestLap": false
        },
        {
          "position": null,
          "code": "LOT",
          "name": "André Lotterer",
          "team": "TAG HEUER PORSCHE FORMULA E TEAM",
          "grid": 1,
          "status": "DNF",
          "points": 3.0,
          "pole": true,
          "fastestLap": false
        },
        {
          "position": null,
          "code": "CAL",
          "name": "James Calado",
          "team": "PANASONIC JAGUAR RACING",
          "grid": 17,
          "status": "DSQ",
          "points": 0.0,
          "pole": false,
          "fastestLap": false
        }
      ],
      "raceId": "5259bb2b-0d65-4cae-ae0d-b047cc910252"
    },
    "5": {
      "race": [
        {
          "position": 1,
          "code": "DAC",
          "name": "António Félix Da Costa",
          "team": "DS TECHEETAH",
          "grid": 1,
          "status": "Finished",
          "points": 28.0,
          "pole": true,
          "fastestLap": false
        },
        {
          "position": 2,
          "code": "GUE",
          "name": "Maximilian Günther",
          "team": "BMW I ANDRETTI MOTORSPORT",
          "grid": 2,
          "status": "Finished",
          "points": 19.0,
          "pole": false,
          "fastestLap": false
        },
        {
          "position": 3,
          "code": "JEV",
          "name": "Jean-Éric Vergne",
          "team": "DS TECHEETAH",
          "grid": 11,
          "status": "Finished",
          "points": 15.0,
          "pole": false,
          "fastestLap": false
        },
        {
          "position": 4,
          "code": "BUE",
          "name": "Sébastien Buemi",
          "team": "NISSAN E.DAMS",
          "grid": 6,
          "status": "Finished",
          "points": 12.0,
          "pole": false,
          "fastestLap": false
        },
        {
          "position": 5,
          "code": "MOR",
          "name": "Edoardo Mortara",
          "team": "ROKIT VENTURI RACING",
          "grid": 5,
          "status": "Finished",
          "points": 10.0,
          "pole": false,
          "fastestLap": false
        },
        {
          "position": 6,
          "code": "EVA",
          "name": "Mitch Evans",
          "team": "PANASONIC JAGUAR RACING",
          "grid": 24,
          "status": "Finished",
          "points": 9.0,
          "pole": false,
          "fastestLap": true
        },
        {
          "position": 7,
          "code": "DIG",
          "name": "Lucas Di Grassi",
          "team": "AUDI SPORT ABT SCHAEFFLER",
          "grid": 13,
          "status": "Finished",
          "points": 6.0,
          "pole": false,
          "fastestLap": false
        },
        {
          "position": 8,
          "code": "LOT",
          "name": "André Lotterer",
          "team": "TAG HEUER PORSCHE FORMULA E TEAM",
          "grid": 3,
          "status": "Finished",
          "points": 4.0,
          "pole": false,
          "fastestLap": false
        },
        {
          "position": 9,
          "code": "ROW",
          "name": "Oliver Rowland",
          "team": "NISSAN E.DAMS",
          "grid": 9,
          "status": "Finished",
          "points": 2.0,
          "pole": false,
          "fastestLap": false
        },
        {
          "position": 10,
          "code": "BIR",
          "name": "Sam Bird",
          "team": "ENVISION VIRGIN RACING",
          "grid": 14,
          "status": "Finished",
          "points": 1.0,
          "pole": false,
          "fastestLap": false
        },
        {
          "position": 11,
          "code": "DEV",
          "name": "Nyck De Vries",
          "team": "MERCEDES-BENZ EQ FORMULA E TEAM",
          "grid": 4,
          "status": "Finished",
          "points": 0.0,
          "pole": false,
          "fastestLap": false
        },
        {
          "position": 12,
          "code": "FRI",
          "name": "Robin Frijns",
          "team": "ENVISION VIRGIN RACING",
          "grid": 22,
          "status": "Finished",
          "points": 0.0,
          "pole": false,
          "fastestLap": false
        },
        {
          "position": 13,
          "code": "DAM",
          "name": "Jérôme D'Ambrosio",
          "team": "Mahindra Racing",
          "grid": 7,
          "status": "Finished",
          "points": 0.0,
          "pole": false,
          "fastestLap": false
        },
        {
          "position": 14,
          "code": "ABT",
          "name": "Daniel Abt",
          "team": "AUDI SPORT ABT SCHAEFFLER",
          "grid": 18,
          "status": "Finished",
          "points": 0.0,
          "pole": false,
          "fastestLap": false
        },
        {
          "position": 15,
          "code": "VAN",
          "name": "Stoffel Vandoorne",
          "team": "MERCEDES-BENZ EQ FORMULA E TEAM",
          "grid": 17,
          "status": "Finished",
          "points": 0.0,
          "pole": false,
          "fastestLap": false
        },
        {
          "position": 16,
          "code": "CAL",
          "name": "James Calado",
          "team": "PANASONIC JAGUAR RACING",
          "grid": 10,
          "status": "Finished",
          "points": 0.0,
          "pole": false,
          "fastestLap": false
        },
        {
          "position": 17,
          "code": "MAS",
          "name": "Felipe Massa",
          "team": "ROKIT VENTURI RACING",
          "grid": 20,
          "status": "Finished",
          "points": 0.0,
          "pole": false,
          "fastestLap": false
        },
        {
          "position": 18,
          "code": "JAN",
          "name": "Neel Jani",
          "team": "TAG HEUER PORSCHE FORMULA E TEAM",
          "grid": 23,
          "status": "Finished",
          "points": 0.0,
          "pole": false,
          "fastestLap": false
        },
        {
          "position": 19,
          "code": "HAR",
          "name": "Brendon Hartley",
          "team": "GEOX DRAGON",
          "grid": 12,
          "status": "Finished",
          "points": 0.0,
          "pole": false,
          "fastestLap": false
        },
        {
          "position": 20,
          "code": "MUE",
          "name": "Nico Müller",
          "team": "GEOX DRAGON",
          "grid": 16,
          "status": "Finished",
          "points": 0.0,
          "pole": false,
          "fastestLap": false
        },
        {
          "position": 21,
          "code": "TUR",
          "name": "Oliver Turvey",
          "team": "NIO 333 FE TEAM",
          "grid": 19,
          "status": "Finished",
          "points": 0.0,
          "pole": false,
          "fastestLap": false
        },
        {
          "position": 22,
          "code": "WEH",
          "name": "Pascal Wehrlein",
          "team": "Mahindra Racing",
          "grid": 15,
          "status": "Finished",
          "points": 0.0,
          "pole": false,
          "fastestLap": false
        },
        {
          "position": 23,
          "code": "QMA",
          "name": "Qinghua Ma",
          "team": "NIO 333 FE TEAM",
          "grid": 21,
          "status": "Finished",
          "points": 0.0,
          "pole": false,
          "fastestLap": false
        },
        {
          "position": null,
          "code": "SIM",
          "name": "Alexander Sims",
          "team": "BMW I ANDRETTI MOTORSPORT",
          "grid": 8,
          "status": "DNF",
          "points": 0.0,
          "pole": false,
          "fastestLap": false
        }
      ],
      "raceId": "71726c0e-453c-456b-8b38-3e3c04ae2ba2"
    },
    "6": {
      "race": [
        {
          "position": 1,
          "code": "DAC",
          "name": "António Félix Da Costa",
          "team": "DS TECHEETAH",
          "grid": 1,
          "status": "Finished",
          "points": 30.0,
          "pole": true,
          "fastestLap": true
        },
        {
          "position": 2,
          "code": "LOT",
          "name": "André Lotterer",
          "team": "TAG HEUER PORSCHE FORMULA E TEAM",
          "grid": 3,
          "status": "Finished",
          "points": 18.0,
          "pole": false,
          "fastestLap": false
        },
        {
          "position": 3,
          "code": "BIR",
          "name": "Sam Bird",
          "team": "ENVISION VIRGIN RACING",
          "grid": 7,
          "status": "Finished",
          "points": 15.0,
          "pole": false,
          "fastestLap": false
        },
        {
          "position": 4,
          "code": "DEV",
          "name": "Nyck De Vries",
          "team": "MERCEDES-BENZ EQ FORMULA E TEAM",
          "grid": 5,
          "status": "Finished",
          "points": 12.0,
          "pole": false,
          "fastestLap": false
        },
        {
          "position": 5,
          "code": "DAM",
          "name": "Jérôme D'Ambrosio",
          "team": "Mahindra Racing",
          "grid": 6,
          "status": "Finished",
          "points": 10.0,
          "pole": false,
          "fastestLap": false
        },
        {
          "position": 6,
          "code": "VAN",
          "name": "Stoffel Vandoorne",
          "team": "MERCEDES-BENZ EQ FORMULA E TEAM",
          "grid": 15,
          "status": "Finished",
          "points": 8.0,
          "pole": false,
          "fastestLap": false
        },
        {
          "position": 7,
          "code": "BUE",
          "name": "Sébastien Buemi",
          "team": "NISSAN E.DAMS",
          "grid": 4,
          "status": "Finished",
          "points": 6.0,
          "pole": false,
          "fastestLap": false
        },
        {
          "position": 8,
          "code": "DIG",
          "name": "Lucas Di Grassi",
          "team": "AUDI SPORT ABT SCHAEFFLER",
          "grid": 20,
          "status": "Finished",
          "points": 4.0,
          "pole": false,
          "fastestLap": false
        },
        {
          "position": 9,
          "code": "SIM",
          "name": "Alexander Sims",
          "team": "BMW I ANDRETTI MOTORSPORT",
          "grid": 16,
          "status": "Finished",
          "points": 2.0,
          "pole": false,
          "fastestLap": false
        },
        {
          "position": 10,
          "code": "RAS",
          "name": "René Rast",
          "team": "AUDI SPORT ABT SCHAEFFLER",
          "grid": 13,
          "status": "Finished",
          "points": 1.0,
          "pole": false,
          "fastestLap": false
        },
        {
          "position": 11,
          "code": "JAN",
          "name": "Neel Jani",
          "team": "TAG HEUER PORSCHE FORMULA E TEAM",
          "grid": 17,
          "status": "Finished",
          "points": 0.0,
          "pole": false,
          "fastestLap": false
        },
        {
          "position": 12,
          "code": "LYN",
          "name": "Alex Lynn",
          "team": "Mahindra Racing",
          "grid": 11,
          "status": "Finished",
          "points": 0.0,
          "pole": false,
          "fastestLap": false
        },
        {
          "position": 13,
          "code": "EVA",
          "name": "Mitch Evans",
          "team": "PANASONIC JAGUAR RACING",
          "grid": 8,
          "status": "Finished",
          "points": 0.0,
          "pole": false,
          "fastestLap": false
        },
        {
          "position": 14,
          "code": "ROW",
          "name": "Oliver Rowland",
          "team": "NISSAN E.DAMS",
          "grid": 23,
          "status": "Finished",
          "points": 0.0,
          "pole": false,
          "fastestLap": false
        },
        {
          "position": 15,
          "code": "CAL",
          "name": "James Calado",
          "team": "PANASONIC JAGUAR RACING",
          "grid": 24,
          "status": "Finished",
          "points": 0.0,
          "pole": false,
          "fastestLap": false
        },
        {
          "position": 16,
          "code": "TUR",
          "name": "Oliver Turvey",
          "team": "NIO 333 FE TEAM",
          "grid": 18,
          "status": "Finished",
          "points": 0.0,
          "pole": false,
          "fastestLap": false
        },
        {
          "position": 17,
          "code": "MOR",
          "name": "Edoardo Mortara",
          "team": "ROKIT VENTURI RACING",
          "grid": 14,
          "status": "Finished",
          "points": 0.0,
          "pole": false,
          "fastestLap": false
        },
        {
          "position": 18,
          "code": "ABT",
          "name": "Daniel Abt",
          "team": "NIO 333 FE TEAM",
          "grid": 21,
          "status": "Finished",
          "points": 0.0,
          "pole": false,
          "fastestLap": false
        },
        {
          "position": null,
          "code": "MAS",
          "name": "Felipe Massa",
          "team": "ROKIT VENTURI RACING",
          "grid": 9,
          "status": "DNF",
          "points": 0.0,
          "pole": false,
          "fastestLap": false
        },
        {
          "position": null,
          "code": "JEV",
          "name": "Jean-Éric Vergne",
          "team": "DS TECHEETAH",
          "grid": 2,
          "status": "Finished",
          "points": 0.0,
          "pole": false,
          "fastestLap": false
        },
        {
          "position": null,
          "code": "GUE",
          "name": "Maximilian Günther",
          "team": "BMW I ANDRETTI MOTORSPORT",
          "grid": 12,
          "status": "DSQ",
          "points": 0.0,
          "pole": false,
          "fastestLap": false
        },
        {
          "position": null,
          "code": "SET",
          "name": "Sérgio Sette Câmara",
          "team": "GEOX DRAGON",
          "grid": 22,
          "status": "DSQ",
          "points": 0.0,
          "pole": false,
          "fastestLap": false
        },
        {
          "position": null,
          "code": "FRI",
          "name": "Robin Frijns",
          "team": "ENVISION VIRGIN RACING",
          "grid": 10,
          "status": "DNF",
          "points": 0.0,
          "pole": false,
          "fastestLap": false
        },
        {
          "position": null,
          "code": "MUE",
          "name": "Nico Müller",
          "team": "GEOX DRAGON",
          "grid": 19,
          "status": "Finished",
          "points": 0.0,
          "pole": false,
          "fastestLap": false
        }
      ],
      "raceId": "7f2e4fae-4d11-4bbe-811d-5e190bbcab3f"
    },
    "7": {
      "race": [
        {
          "position": 1,
          "code": "DAC",
          "name": "António Félix Da Costa",
          "team": "DS TECHEETAH",
          "grid": 1,
          "status": "Finished",
          "points": 28.0,
          "pole": true,
          "fastestLap": false
        },
        {
          "position": 2,
          "code": "BUE",
          "name": "Sébastien Buemi",
          "team": "NISSAN E.DAMS",
          "grid": 2,
          "status": "Finished",
          "points": 19.0,
          "pole": false,
          "fastestLap": false
        },
        {
          "position": 3,
          "code": "DIG",
          "name": "Lucas Di Grassi",
          "team": "AUDI SPORT ABT SCHAEFFLER",
          "grid": 6,
          "status": "Finished",
          "points": 15.0,
          "pole": false,
          "fastestLap": false
        },
        {
          "position": 4,
          "code": "FRI",
          "name": "Robin Frijns",
          "team": "ENVISION VIRGIN RACING",
          "grid": 5,
          "status": "Finished",
          "points": 12.0,
          "pole": false,
          "fastestLap": false
        },
        {
          "position": 5,
          "code": "VAN",
          "name": "Stoffel Vandoorne",
          "team": "MERCEDES-BENZ EQ FORMULA E TEAM",
          "grid": 13,
          "status": "Finished",
          "points": 11.0,
          "pole": false,
          "fastestLap": true
        },
        {
          "position": 6,
          "code": "BIR",
          "name": "Sam Bird",
          "team": "ENVISION VIRGIN RACING",
          "grid": 9,
          "status": "Finished",
          "points": 8.0,
          "pole": false,
          "fastestLap": false
        },
        {
          "position": 7,
          "code": "ROW",
          "name": "Oliver Rowland",
          "team": "NISSAN E.DAMS",
          "grid": 7,
          "status": "Finished",
          "points": 6.0,
          "pole": false,
          "fastestLap": false
        },
        {
          "position": 8,
          "code": "MOR",
          "name": "Edoardo Mortara",
          "team": "ROKIT VENTURI RACING",
          "grid": 10,
          "status": "Finished",
          "points": 4.0,
          "pole": false,
          "fastestLap": false
        },
        {
          "position": 9,
          "code": "LOT",
          "name": "André Lotterer",
          "team": "TAG HEUER PORSCHE FORMULA E TEAM",
          "grid": 12,
          "status": "Finished",
          "points": 2.0,
          "pole": false,
          "fastestLap": false
        },
        {
          "position": 10,
          "code": "JEV",
          "name": "Jean-Éric Vergne",
          "team": "DS TECHEETAH",
          "grid": 8,
          "status": "Finished",
          "points": 1.0,
          "pole": false,
          "fastestLap": false
        },
        {
          "position": 11,
          "code": "LYN",
          "name": "Alex Lynn",
          "team": "Mahindra Racing",
          "grid": 3,
          "status": "Finished",
          "points": 0.0,
          "pole": false,
          "fastestLap": false
        },
        {
          "position": 12,
          "code": "EVA",
          "name": "Mitch Evans",
          "team": "PANASONIC JAGUAR RACING",
          "grid": 16,
          "status": "Finished",
          "points": 0.0,
          "pole": false,
          "fastestLap": false
        },
        {
          "position": 13,
          "code": "RAS",
          "name": "René Rast",
          "team": "AUDI SPORT ABT SCHAEFFLER",
          "grid": 23,
          "status": "Finished",
          "points": 0.0,
          "pole": false,
          "fastestLap": false
        },
        {
          "position": 14,
          "code": "MUE",
          "name": "Nico Müller",
          "team": "GEOX DRAGON",
          "grid": 18,
          "status": "Finished",
          "points": 0.0,
          "pole": false,
          "fastestLap": false
        },
        {
          "position": 15,
          "code": "JAN",
          "name": "Neel Jani",
          "team": "TAG HEUER PORSCHE FORMULA E TEAM",
          "grid": 19,
          "status": "Finished",
          "points": 0.0,
          "pole": false,
          "fastestLap": false
        },
        {
          "position": 16,
          "code": "ABT",
          "name": "Daniel Abt",
          "team": "NIO 333 FE TEAM",
          "grid": 21,
          "status": "Finished",
          "points": 0.0,
          "pole": false,
          "fastestLap": false
        },
        {
          "position": 17,
          "code": "SET",
          "name": "Sérgio Sette Câmara",
          "team": "GEOX DRAGON",
          "grid": 20,
          "status": "Finished",
          "points": 0.0,
          "pole": false,
          "fastestLap": false
        },
        {
          "position": 18,
          "code": "TUR",
          "name": "Oliver Turvey",
          "team": "NIO 333 FE TEAM",
          "grid": 15,
          "status": "Finished",
          "points": 0.0,
          "pole": false,
          "fastestLap": false
        },
        {
          "position": 19,
          "code": "SIM",
          "name": "Alexander Sims",
          "team": "BMW I ANDRETTI MOTORSPORT",
          "grid": 24,
          "status": "Finished",
          "points": 0.0,
          "pole": false,
          "fastestLap": false
        },
        {
          "position": 20,
          "code": "CAL",
          "name": "James Calado",
          "team": "PANASONIC JAGUAR RACING",
          "grid": 22,
          "status": "Finished",
          "points": 0.0,
          "pole": false,
          "fastestLap": false
        },
        {
          "position": null,
          "code": "DAM",
          "name": "Jérôme D'Ambrosio",
          "team": "Mahindra Racing",
          "grid": 14,
          "status": "DSQ",
          "points": 0.0,
          "pole": false,
          "fastestLap": false
        },
        {
          "position": null,
          "code": "MAS",
          "name": "Felipe Massa",
          "team": "ROKIT VENTURI RACING",
          "grid": 17,
          "status": "Finished",
          "points": 0.0,
          "pole": false,
          "fastestLap": false
        },
        {
          "position": null,
          "code": "DEV",
          "name": "Nyck De Vries",
          "team": "MERCEDES-BENZ EQ FORMULA E TEAM",
          "grid": 4,
          "status": "DNF",
          "points": 0.0,
          "pole": false,
          "fastestLap": false
        },
        {
          "position": null,
          "code": "GUE",
          "name": "Maximilian Günther",
          "team": "BMW I ANDRETTI MOTORSPORT",
          "grid": 11,
          "status": "DNF",
          "points": 0.0,
          "pole": false,
          "fastestLap": false
        }
      ],
      "raceId": "3c6847e1-6e8f-43a1-b1d6-38e4d8126f8a"
    },
    "8": {
      "race": [
        {
          "position": 1,
          "code": "GUE",
          "name": "Maximilian Günther",
          "team": "BMW I ANDRETTI MOTORSPORT",
          "grid": 2,
          "status": "Finished",
          "points": 25.0,
          "pole": false,
          "fastestLap": false
        },
        {
          "position": 2,
          "code": "FRI",
          "name": "Robin Frijns",
          "team": "ENVISION VIRGIN RACING",
          "grid": 6,
          "status": "Finished",
          "points": 18.0,
          "pole": false,
          "fastestLap": false
        },
        {
          "position": 3,
          "code": "JEV",
          "name": "Jean-Éric Vergne",
          "team": "DS TECHEETAH",
          "grid": 1,
          "status": "Finished",
          "points": 19.0,
          "pole": true,
          "fastestLap": false
        },
        {
          "position": 4,
          "code": "DAC",
          "name": "António Félix Da Costa",
          "team": "DS TECHEETAH",
          "grid": 8,
          "status": "Finished",
          "points": 12.0,
          "pole": false,
          "fastestLap": false
        },
        {
          "position": 5,
          "code": "LOT",
          "name": "André Lotterer",
          "team": "TAG HEUER PORSCHE FORMULA E TEAM",
          "grid": 7,
          "status": "Finished",
          "points": 10.0,
          "pole": false,
          "fastestLap": false
        },
        {
          "position": 6,
          "code": "ROW",
          "name": "Oliver Rowland",
          "team": "NISSAN E.DAMS",
          "grid": 9,
          "status": "Finished",
          "points": 8.0,
          "pole": false,
          "fastestLap": false
        },
        {
          "position": 7,
          "code": "DAM",
          "name": "Jérôme D'Ambrosio",
          "team": "Mahindra Racing",
          "grid": 3,
          "status": "Finished",
          "points": 6.0,
          "pole": false,
          "fastestLap": false
        },
        {
          "position": 8,
          "code": "DIG",
          "name": "Lucas Di Grassi",
          "team": "AUDI SPORT ABT SCHAEFFLER",
          "grid": 10,
          "status": "Finished",
          "points": 4.0,
          "pole": false,
          "fastestLap": false
        },
        {
          "position": 9,
          "code": "EVA",
          "name": "Mitch Evans",
          "team": "PANASONIC JAGUAR RACING",
          "grid": 19,
          "status": "Finished",
          "points": 3.0,
          "pole": false,
          "fastestLap": true
        },
        {
          "position": 10,
          "code": "SIM",
          "name": "Alexander Sims",
          "team": "BMW I ANDRETTI MOTORSPORT",
          "grid": 16,
          "status": "Finished",
          "points": 1.0,
          "pole": false,
          "fastestLap": false
        },
        {
          "position": 11,
          "code": "BUE",
          "name": "Sébastien Buemi",
          "team": "NISSAN E.DAMS",
          "grid": 15,
          "status": "Finished",
          "points": 0.0,
          "pole": false,
          "fastestLap": false
        },
        {
          "position": 12,
          "code": "MUE",
          "name": "Nico Müller",
          "team": "GEOX DRAGON",
          "grid": 23,
          "status": "Finished",
          "points": 0.0,
          "pole": false,
          "fastestLap": false
        },
        {
          "position": 13,
          "code": "BIR",
          "name": "Sam Bird",
          "team": "ENVISION VIRGIN RACING",
          "grid": 20,
          "status": "Finished",
          "points": 0.0,
          "pole": false,
          "fastestLap": false
        },
        {
          "position": 14,
          "code": "MOR",
          "name": "Edoardo Mortara",
          "team": "ROKIT VENTURI RACING",
          "grid": 14,
          "status": "Finished",
          "points": 0.0,
          "pole": false,
          "fastestLap": false
        },
        {
          "position": 15,
          "code": "ABT",
          "name": "Daniel Abt",
          "team": "NIO 333 FE TEAM",
          "grid": 22,
          "status": "Finished",
          "points": 0.0,
          "pole": false,
          "fastestLap": false
        },
        {
          "position": 16,
          "code": "TUR",
          "name": "Oliver Turvey",
          "team": "NIO 333 FE TEAM",
          "grid": 24,
          "status": "Finished",
          "points": 0.0,
          "pole": false,
          "fastestLap": false
        },
        {
          "position": 17,
          "code": "LYN",
          "name": "Alex Lynn",
          "team": "Mahindra Racing",
          "grid": 5,
          "status": "Finished",
          "points": 0.0,
          "pole": false,
          "fastestLap": false
        },
        {
          "position": 18,
          "code": "DEV",
          "name": "Nyck De Vries",
          "team": "MERCEDES-BENZ EQ FORMULA E TEAM",
          "grid": 13,
          "status": "Finished",
          "points": 0.0,
          "pole": false,
          "fastestLap": false
        },
        {
          "position": 19,
          "code": "MAS",
          "name": "Felipe Massa",
          "team": "ROKIT VENTURI RACING",
          "grid": 12,
          "status": "Finished",
          "points": 0.0,
          "pole": false,
          "fastestLap": false
        },
        {
          "position": null,
          "code": "VAN",
          "name": "Stoffel Vandoorne",
          "team": "MERCEDES-BENZ EQ FORMULA E TEAM",
          "grid": 4,
          "status": "DNF",
          "points": 0.0,
          "pole": false,
          "fastestLap": false
        },
        {
          "position": null,
          "code": "JAN",
          "name": "Neel Jani",
          "team": "TAG HEUER PORSCHE FORMULA E TEAM",
          "grid": 18,
          "status": "DNF",
          "points": 0.0,
          "pole": false,
          "fastestLap": false
        },
        {
          "position": null,
          "code": "SET",
          "name": "Sérgio Sette Câmara",
          "team": "GEOX DRAGON",
          "grid": 11,
          "status": "DNF",
          "points": 0.0,
          "pole": false,
          "fastestLap": false
        },
        {
          "position": null,
          "code": "RAS",
          "name": "René Rast",
          "team": "AUDI SPORT ABT SCHAEFFLER",
          "grid": 21,
          "status": "DNF",
          "points": 0.0,
          "pole": false,
          "fastestLap": false
        },
        {
          "position": null,
          "code": "CAL",
          "name": "James Calado",
          "team": "PANASONIC JAGUAR RACING",
          "grid": 17,
          "status": "DNF",
          "points": 0.0,
          "pole": false,
          "fastestLap": false
        }
      ],
      "raceId": "92b4e8b0-4192-403e-ae87-00c7e7c34511"
    },
    "9": {
      "race": [
        {
          "position": 1,
          "code": "JEV",
          "name": "Jean-Éric Vergne",
          "team": "DS TECHEETAH",
          "grid": 1,
          "status": "Finished",
          "points": 29.0,
          "pole": true,
          "fastestLap": false
        },
        {
          "position": 2,
          "code": "DAC",
          "name": "António Félix Da Costa",
          "team": "DS TECHEETAH",
          "grid": 2,
          "status": "Finished",
          "points": 19.0,
          "pole": false,
          "fastestLap": true
        },
        {
          "position": 3,
          "code": "BUE",
          "name": "Sébastien Buemi",
          "team": "NISSAN E.DAMS",
          "grid": 4,
          "status": "Finished",
          "points": 15.0,
          "pole": false,
          "fastestLap": false
        },
        {
          "position": 4,
          "code": "DEV",
          "name": "Nyck De Vries",
          "team": "MERCEDES-BENZ EQ FORMULA E TEAM",
          "grid": 5,
          "status": "Finished",
          "points": 12.0,
          "pole": false,
          "fastestLap": false
        },
        {
          "position": 5,
          "code": "ROW",
          "name": "Oliver Rowland",
          "team": "NISSAN E.DAMS",
          "grid": 3,
          "status": "Finished",
          "points": 10.0,
          "pole": false,
          "fastestLap": false
        },
        {
          "position": 6,
          "code": "DIG",
          "name": "Lucas Di Grassi",
          "team": "AUDI SPORT ABT SCHAEFFLER",
          "grid": 12,
          "status": "Finished",
          "points": 8.0,
          "pole": false,
          "fastestLap": false
        },
        {
          "position": 7,
          "code": "EVA",
          "name": "Mitch Evans",
          "team": "PANASONIC JAGUAR RACING",
          "grid": 11,
          "status": "Finished",
          "points": 6.0,
          "pole": false,
          "fastestLap": false
        },
        {
          "position": 8,
          "code": "LOT",
          "name": "André Lotterer",
          "team": "TAG HEUER PORSCHE FORMULA E TEAM",
          "grid": 18,
          "status": "Finished",
          "points": 4.0,
          "pole": false,
          "fastestLap": false
        },
        {
          "position": 9,
          "code": "LYN",
          "name": "Alex Lynn",
          "team": "Mahindra Racing",
          "grid": 7,
          "status": "Finished",
          "points": 2.0,
          "pole": false,
          "fastestLap": false
        },
        {
          "position": 10,
          "code": "MAS",
          "name": "Felipe Massa",
          "team": "ROKIT VENTURI RACING",
          "grid": 6,
          "status": "Finished",
          "points": 1.0,
          "pole": false,
          "fastestLap": false
        },
        {
          "position": 11,
          "code": "BIR",
          "name": "Sam Bird",
          "team": "ENVISION VIRGIN RACING",
          "grid": 17,
          "status": "Finished",
          "points": 0.0,
          "pole": false,
          "fastestLap": false
        },
        {
          "position": 12,
          "code": "VAN",
          "name": "Stoffel Vandoorne",
          "team": "MERCEDES-BENZ EQ FORMULA E TEAM",
          "grid": 20,
          "status": "Finished",
          "points": 0.0,
          "pole": false,
          "fastestLap": false
        },
        {
          "position": 13,
          "code": "SIM",
          "name": "Alexander Sims",
          "team": "BMW I ANDRETTI MOTORSPORT",
          "grid": 16,
          "status": "Finished",
          "points": 0.0,
          "pole": false,
          "fastestLap": false
        },
        {
          "position": 14,
          "code": "MOR",
          "name": "Edoardo Mortara",
          "team": "ROKIT VENTURI RACING",
          "grid": 13,
          "status": "Finished",
          "points": 0.0,
          "pole": false,
          "fastestLap": false
        },
        {
          "position": 15,
          "code": "DAM",
          "name": "Jérôme D'Ambrosio",
          "team": "Mahindra Racing",
          "grid": 9,
          "status": "Finished",
          "points": 0.0,
          "pole": false,
          "fastestLap": false
        },
        {
          "position": 16,
          "code": "RAS",
          "name": "René Rast",
          "team": "AUDI SPORT ABT SCHAEFFLER",
          "grid": 8,
          "status": "Finished",
          "points": 0.0,
          "pole": false,
          "fastestLap": false
        },
        {
          "position": 17,
          "code": "CAL",
          "name": "James Calado",
          "team": "PANASONIC JAGUAR RACING",
          "grid": 14,
          "status": "Finished",
          "points": 0.0,
          "pole": false,
          "fastestLap": false
        },
        {
          "position": 18,
          "code": "ABT",
          "name": "Daniel Abt",
          "team": "NIO 333 FE TEAM",
          "grid": 23,
          "status": "Finished",
          "points": 0.0,
          "pole": false,
          "fastestLap": false
        },
        {
          "position": 19,
          "code": "JAN",
          "name": "Neel Jani",
          "team": "TAG HEUER PORSCHE FORMULA E TEAM",
          "grid": 22,
          "status": "Finished",
          "points": 0.0,
          "pole": false,
          "fastestLap": false
        },
        {
          "position": 20,
          "code": "MUE",
          "name": "Nico Müller",
          "team": "GEOX DRAGON",
          "grid": 15,
          "status": "Finished",
          "points": 0.0,
          "pole": false,
          "fastestLap": false
        },
        {
          "position": 21,
          "code": "SET",
          "name": "Sérgio Sette Câmara",
          "team": "GEOX DRAGON",
          "grid": 24,
          "status": "Finished",
          "points": 0.0,
          "pole": false,
          "fastestLap": false
        },
        {
          "position": 22,
          "code": "TUR",
          "name": "Oliver Turvey",
          "team": "NIO 333 FE TEAM",
          "grid": 19,
          "status": "Finished",
          "points": 0.0,
          "pole": false,
          "fastestLap": false
        },
        {
          "position": null,
          "code": "GUE",
          "name": "Maximilian Günther",
          "team": "BMW I ANDRETTI MOTORSPORT",
          "grid": 21,
          "status": "Finished",
          "points": 0.0,
          "pole": false,
          "fastestLap": false
        },
        {
          "position": null,
          "code": "FRI",
          "name": "Robin Frijns",
          "team": "ENVISION VIRGIN RACING",
          "grid": 10,
          "status": "DNS",
          "points": 0.0,
          "pole": false,
          "fastestLap": false
        }
      ],
      "raceId": "c54d37fb-9b6a-411b-a8e1-7e1135cf8e6d"
    },
    "10": {
      "race": [
        {
          "position": 1,
          "code": "ROW",
          "name": "Oliver Rowland",
          "team": "NISSAN E.DAMS",
          "grid": 1,
          "status": "Finished",
          "points": 29.0,
          "pole": true,
          "fastestLap": true
        },
        {
          "position": 2,
          "code": "FRI",
          "name": "Robin Frijns",
          "team": "ENVISION VIRGIN RACING",
          "grid": 2,
          "status": "Finished",
          "points": 18.0,
          "pole": false,
          "fastestLap": false
        },
        {
          "position": 3,
          "code": "RAS",
          "name": "René Rast",
          "team": "AUDI SPORT ABT SCHAEFFLER",
          "grid": 4,
          "status": "Finished",
          "points": 16.0,
          "pole": false,
          "fastestLap": false
        },
        {
          "position": 4,
          "code": "LOT",
          "name": "André Lotterer",
          "team": "TAG HEUER PORSCHE FORMULA E TEAM",
          "grid": 7,
          "status": "Finished",
          "points": 12.0,
          "pole": false,
          "fastestLap": false
        },
        {
          "position": 5,
          "code": "LYN",
          "name": "Alex Lynn",
          "team": "Mahindra Racing",
          "grid": 5,
          "status": "Finished",
          "points": 10.0,
          "pole": false,
          "fastestLap": false
        },
        {
          "position": 6,
          "code": "JAN",
          "name": "Neel Jani",
          "team": "TAG HEUER PORSCHE FORMULA E TEAM",
          "grid": 3,
          "status": "Finished",
          "points": 8.0,
          "pole": false,
          "fastestLap": false
        },
        {
          "position": 7,
          "code": "EVA",
          "name": "Mitch Evans",
          "team": "PANASONIC JAGUAR RACING",
          "grid": 13,
          "status": "Finished",
          "points": 6.0,
          "pole": false,
          "fastestLap": false
        },
        {
          "position": 8,
          "code": "MOR",
          "name": "Edoardo Mortara",
          "team": "ROKIT VENTURI RACING",
          "grid": 10,
          "status": "Finished",
          "points": 4.0,
          "pole": false,
          "fastestLap": false
        },
        {
          "position": 9,
          "code": "VAN",
          "name": "Stoffel Vandoorne",
          "team": "MERCEDES-BENZ EQ FORMULA E TEAM",
          "grid": 18,
          "status": "Finished",
          "points": 2.0,
          "pole": false,
          "fastestLap": false
        },
        {
          "position": 10,
          "code": "BUE",
          "name": "Sébastien Buemi",
          "team": "NISSAN E.DAMS",
          "grid": 22,
          "status": "Finished",
          "points": 1.0,
          "pole": false,
          "fastestLap": false
        },
        {
          "position": 11,
          "code": "SIM",
          "name": "Alexander Sims",
          "team": "BMW I ANDRETTI MOTORSPORT",
          "grid": 14,
          "status": "Finished",
          "points": 0.0,
          "pole": false,
          "fastestLap": false
        },
        {
          "position": 12,
          "code": "BLO",
          "name": "Tom Blomqvist",
          "team": "PANASONIC JAGUAR RACING",
          "grid": 6,
          "status": "Finished",
          "points": 0.0,
          "pole": false,
          "fastestLap": false
        },
        {
          "position": 13,
          "code": "MAS",
          "name": "Felipe Massa",
          "team": "ROKIT VENTURI RACING",
          "grid": 8,
          "status": "Finished",
          "points": 0.0,
          "pole": false,
          "fastestLap": false
        },
        {
          "position": 14,
          "code": "DEV",
          "name": "Nyck De Vries",
          "team": "MERCEDES-BENZ EQ FORMULA E TEAM",
          "grid": 19,
          "status": "Finished",
          "points": 0.0,
          "pole": false,
          "fastestLap": false
        },
        {
          "position": 15,
          "code": "SET",
          "name": "Sérgio Sette Câmara",
          "team": "GEOX DRAGON",
          "grid": 9,
          "status": "Finished",
          "points": 0.0,
          "pole": false,
          "fastestLap": false
        },
        {
          "position": 16,
          "code": "DAM",
          "name": "Jérôme D'Ambrosio",
          "team": "Mahindra Racing",
          "grid": 17,
          "status": "Finished",
          "points": 0.0,
          "pole": false,
          "fastestLap": false
        },
        {
          "position": 17,
          "code": "MUE",
          "name": "Nico Müller",
          "team": "GEOX DRAGON",
          "grid": 11,
          "status": "Finished",
          "points": 0.0,
          "pole": false,
          "fastestLap": false
        },
        {
          "position": 18,
          "code": "JEV",
          "name": "Jean-Éric Vergne",
          "team": "DS TECHEETAH",
          "grid": 24,
          "status": "Finished",
          "points": 0.0,
          "pole": false,
          "fastestLap": false
        },
        {
          "position": 19,
          "code": "TUR",
          "name": "Oliver Turvey",
          "team": "NIO 333 FE TEAM",
          "grid": 12,
          "status": "Finished",
          "points": 0.0,
          "pole": false,
          "fastestLap": false
        },
        {
          "position": 20,
          "code": "BIR",
          "name": "Sam Bird",
          "team": "ENVISION VIRGIN RACING",
          "grid": 15,
          "status": "Finished",
          "points": 0.0,
          "pole": false,
          "fastestLap": false
        },
        {
          "position": 21,
          "code": "DIG",
          "name": "Lucas Di Grassi",
          "team": "AUDI SPORT ABT SCHAEFFLER",
          "grid": 23,
          "status": "Finished",
          "points": 0.0,
          "pole": false,
          "fastestLap": false
        },
        {
          "position": null,
          "code": "GUE",
          "name": "Maximilian Günther",
          "team": "BMW I ANDRETTI MOTORSPORT",
          "grid": 16,
          "status": "Finished",
          "points": 0.0,
          "pole": false,
          "fastestLap": false
        },
        {
          "position": null,
          "code": "ABT",
          "name": "Daniel Abt",
          "team": "NIO 333 FE TEAM",
          "grid": 20,
          "status": "DNF",
          "points": 0.0,
          "pole": false,
          "fastestLap": false
        },
        {
          "position": null,
          "code": "DAC",
          "name": "António Félix Da Costa",
          "team": "DS TECHEETAH",
          "grid": 21,
          "status": "DNF",
          "points": 0.0,
          "pole": false,
          "fastestLap": false
        }
      ],
      "raceId": "f44c8356-840d-42cc-9045-6ec79380b062"
    },
    "11": {
      "race": [
        {
          "position": 1,
          "code": "VAN",
          "name": "Stoffel Vandoorne",
          "team": "MERCEDES-BENZ EQ FORMULA E TEAM",
          "grid": 1,
          "status": "Finished",
          "points": 28.0,
          "pole": true,
          "fastestLap": false
        },
        {
          "position": 2,
          "code": "DEV",
          "name": "Nyck De Vries",
          "team": "MERCEDES-BENZ EQ FORMULA E TEAM",
          "grid": 4,
          "status": "Finished",
          "points": 18.0,
          "pole": false,
          "fastestLap": false
        },
        {
          "position": 3,
          "code": "BUE",
          "name": "Sébastien Buemi",
          "team": "NISSAN E.DAMS",
          "grid": 2,
          "status": "Finished",
          "points": 16.0,
          "pole": false,
          "fastestLap": false
        },
        {
          "position": 4,
          "code": "RAS",
          "name": "René Rast",
          "team": "AUDI SPORT ABT SCHAEFFLER",
          "grid": 3,
          "status": "Finished",
          "points": 12.0,
          "pole": false,
          "fastestLap": false
        },
        {
          "position": 5,
          "code": "BIR",
          "name": "Sam Bird",
          "team": "ENVISION VIRGIN RACING",
          "grid": 14,
          "status": "Finished",
          "points": 11.0,
          "pole": false,
          "fastestLap": true
        },
        {
          "position": 6,
          "code": "DIG",
          "name": "Lucas Di Grassi",
          "team": "AUDI SPORT ABT SCHAEFFLER",
          "grid": 10,
          "status": "Finished",
          "points": 8.0,
          "pole": false,
          "fastestLap": false
        },
        {
          "position": 7,
          "code": "JEV",
          "name": "Jean-Éric Vergne",
          "team": "DS TECHEETAH",
          "grid": 21,
          "status": "Finished",
          "points": 6.0,
          "pole": false,
          "fastestLap": false
        },
        {
          "position": 8,
          "code": "LYN",
          "name": "Alex Lynn",
          "team": "Mahindra Racing",
          "grid": 7,
          "status": "Finished",
          "points": 4.0,
          "pole": false,
          "fastestLap": false
        },
        {
          "position": 9,
          "code": "DAC",
          "name": "António Félix Da Costa",
          "team": "DS TECHEETAH",
          "grid": 19,
          "status": "Finished",
          "points": 2.0,
          "pole": false,
          "fastestLap": false
        },
        {
          "position": 10,
          "code": "MOR",
          "name": "Edoardo Mortara",
          "team": "ROKIT VENTURI RACING",
          "grid": 6,
          "status": "Finished",
          "points": 1.0,
          "pole": false,
          "fastestLap": false
        },
        {
          "position": 11,
          "code": "EVA",
          "name": "Mitch Evans",
          "team": "PANASONIC JAGUAR RACING",
          "grid": 23,
          "status": "Finished",
          "points": 0.0,
          "pole": false,
          "fastestLap": false
        },
        {
          "position": 12,
          "code": "GUE",
          "name": "Maximilian Günther",
          "team": "BMW I ANDRETTI MOTORSPORT",
          "grid": 18,
          "status": "Finished",
          "points": 0.0,
          "pole": false,
          "fastestLap": false
        },
        {
          "position": 13,
          "code": "SIM",
          "name": "Alexander Sims",
          "team": "BMW I ANDRETTI MOTORSPORT",
          "grid": 15,
          "status": "Finished",
          "points": 0.0,
          "pole": false,
          "fastestLap": false
        },
        {
          "position": 14,
          "code": "LOT",
          "name": "André Lotterer",
          "team": "TAG HEUER PORSCHE FORMULA E TEAM",
          "grid": 20,
          "status": "Finished",
          "points": 0.0,
          "pole": false,
          "fastestLap": false
        },
        {
          "position": 15,
          "code": "JAN",
          "name": "Neel Jani",
          "team": "TAG HEUER PORSCHE FORMULA E TEAM",
          "grid": 8,
          "status": "Finished",
          "points": 0.0,
          "pole": false,
          "fastestLap": false
        },
        {
          "position": 16,
          "code": "MAS",
          "name": "Felipe Massa",
          "team": "ROKIT VENTURI RACING",
          "grid": 11,
          "status": "Finished",
          "points": 0.0,
          "pole": false,
          "fastestLap": false
        },
        {
          "position": 17,
          "code": "BLO",
          "name": "Tom Blomqvist",
          "team": "PANASONIC JAGUAR RACING",
          "grid": 12,
          "status": "Finished",
          "points": 0.0,
          "pole": false,
          "fastestLap": false
        },
        {
          "position": 18,
          "code": "DAM",
          "name": "Jérôme D'Ambrosio",
          "team": "Mahindra Racing",
          "grid": 16,
          "status": "Finished",
          "points": 0.0,
          "pole": false,
          "fastestLap": false
        },
        {
          "position": 19,
          "code": "SET",
          "name": "Sérgio Sette Câmara",
          "team": "GEOX DRAGON",
          "grid": 9,
          "status": "Finished",
          "points": 0.0,
          "pole": false,
          "fastestLap": false
        },
        {
          "position": 20,
          "code": "ABT",
          "name": "Daniel Abt",
          "team": "NIO 333 FE TEAM",
          "grid": 17,
          "status": "Finished",
          "points": 0.0,
          "pole": false,
          "fastestLap": false
        },
        {
          "position": 21,
          "code": "TUR",
          "name": "Oliver Turvey",
          "team": "NIO 333 FE TEAM",
          "grid": 13,
          "status": "Finished",
          "points": 0.0,
          "pole": false,
          "fastestLap": false
        },
        {
          "position": 22,
          "code": "MUE",
          "name": "Nico Müller",
          "team": "GEOX DRAGON",
          "grid": 22,
          "status": "Finished",
          "points": 0.0,
          "pole": false,
          "fastestLap": false
        },
        {
          "position": null,
          "code": "ROW",
          "name": "Oliver Rowland",
          "team": "NISSAN E.DAMS",
          "grid": 24,
          "status": "DNF",
          "points": 0.0,
          "pole": false,
          "fastestLap": false
        },
        {
          "position": null,
          "code": "FRI",
          "name": "Robin Frijns",
          "team": "ENVISION VIRGIN RACING",
          "grid": 5,
          "status": "DNF",
          "points": 0.0,
          "pole": false,
          "fastestLap": false
        }
      ],
      "raceId": "97b4c0d9-1f03-484e-a3c6-7e9365d1d895"
    }
  }
}
