{
  "season": 2025,
  "rounds": [
    {
      "season": 2025,
      "round": 1,
      "drivers_compared": 14,
      "mean_position_error": 6.571428571428571,
      "median_position_error": 6.0,
      "rmse_position_error": 8.400680244565232,
      "exact_matches": 1,
      "within_3": 4,
      "within_5": 7,
      "winner_hit": false,
      "podium_hits": 1,
      "mean_signed_delta": 1.2857142857142858,
      "spearman_correlation": -0.1254299226812827,
      "ndcg_at_5": 0.423083630189365,
      "biggest_misses": [
        {
          "driver": "NOR",
          "predicted": 18,
          "actual": 1,
          "delta": 17,
          "absDelta": 17
        },
        {
          "driver": "ALO",
          "predicted": 3,
          "actual": 17,
          "delta": -14,
          "absDelta": 14
        },
        {
          "driver": "SAI",
          "predicted": 5,
          "actual": 18,
          "delta": -13,
          "absDelta": 13
        },
        {
          "driver": "PIA",
          "predicted": 20,
          "actual": 9,
          "delta": 11,
          "absDelta": 11
        },
        {
          "driver": "HUL",
          "predicted": 16,
          "actual": 7,
          "delta": 9,
          "absDelta": 9
        }
      ]
    },
    {
      "season": 2025,
      "round": 2,
      "drivers_compared": 18,
      "mean_position_error": 9.0,
      "median_position_error": 7.0,
      "rmse_position_error": 10.208928554075703,
      "exact_matches": 0,
      "within_3": 2,
      "within_5": 4,
      "winner_hit": false,
      "podium_hits": 0,
      "mean_signed_delta": 4.555555555555555,
      "spearman_correlation": -0.10497352134130927,
      "ndcg_at_5": 0.2231353605218925,
      "biggest_misses": [
        {
          "driver": "ANT",
          "predicted": 24,
          "actual": 6,
          "delta": 18,
          "absDelta": 18
        },
        {
          "driver": "NOR",
          "predicted": 18,
          "actual": 2,
          "delta": 16,
          "absDelta": 16
        },
        {
          "driver": "ALO",
          "predicted": 2,
          "actual": 17,
          "delta": -15,
          "absDelta": 15
        },
        {
          "driver": "ALB",
          "predicted": 22,
          "actual": 7,
          "delta": 15,
          "absDelta": 15
        },
        {
          "driver": "BEA",
          "predicted": 23,
          "actual": 8,
          "delta": 15,
          "absDelta": 15
        }
      ]
    },
    {
      "season": 2025,
      "round": 3,
      "drivers_compared": 20,
      "mean_position_error": 8.2,
      "median_position_error": 7.0,
      "rmse_position_error": 9.731392500562292,
      "exact_matches": 0,
      "within_3": 2,
      "within_5": 7,
      "winner_hit": false,
      "podium_hits": 2,
      "mean_signed_delta": 6.0,
      "spearman_correlation": 0.11729323308270677,
      "ndcg_at_5": 0.6208529597763213,
      "biggest_misses": [
        {
          "driver": "ANT",
          "predicted": 25,
          "actual": 6,
          "delta": 19,
          "absDelta": 19
        },
        {
          "driver": "LEC",
          "predicted": 22,
          "actual": 4,
          "delta": 18,
          "absDelta": 18
        },
        {
          "driver": "ALB",
          "predicted": 26,
          "actual": 9,
          "delta": 17,
          "absDelta": 17
        },
        {
          "driver": "BEA",
          "predicted": 24,
          "actual": 10,
          "delta": 14,
          "absDelta": 14
        },
        {
          "driver": "RUS",
          "predicted": 17,
          "actual": 5,
          "delta": 12,
          "absDelta": 12
        }
      ]
    },
    {
      "season": 2025,
      "round": 4,
      "drivers_compared": 20,
      "mean_position_error": 7.8,
      "median_position_error": 8.0,
      "rmse_position_error": 8.567379996241558,
      "exact_matches": 0,
      "within_3": 3,
      "within_5": 6,
      "winner_hit": false,
      "podium_hits": 0,
      "mean_signed_delta": 0.0,
      "spearman_correlation": -0.1037593984962406,
      "ndcg_at_5": 0.0,
      "biggest_misses": [
        {
          "driver": "LAW",
          "predicted": 3,
          "actual": 16,
          "delta": -13,
          "absDelta": 13
        },
        {
          "driver": "GAS",
          "predicted": 20,
          "actual": 7,
          "delta": 13,
          "absDelta": 13
        },
        {
          "driver": "HAD",
          "predicted": 1,
          "actual": 13,
          "delta": -12,
          "absDelta": 12
        },
        {
          "driver": "DOO",
          "predicted": 2,
          "actual": 14,
          "delta": -12,
          "absDelta": 12
        },
        {
          "driver": "BOR",
          "predicted": 6,
          "actual": 18,
          "delta": -12,
          "absDelta": 12
        }
      ]
    },
    {
      "season": 2025,
      "round": 5,
      "drivers_compared": 20,
      "mean_position_error": 6.9,
      "median_position_error": 7.0,
      "rmse_position_error": 7.930952023559341,
      "exact_matches": 0,
      "within_3": 4,
      "within_5": 7,
      "winner_hit": false,
      "podium_hits": 2,
      "mean_signed_delta": 6.0,
      "spearman_correlation": 0.5954887218045113,
      "ndcg_at_5": 0.8002768815416859,
      "biggest_misses": [
        {
          "driver": "ALO",
          "predicted": 26,
          "actual": 11,
          "delta": 15,
          "absDelta": 15
        },
        {
          "driver": "ANT",
          "predicted": 20,
          "actual": 6,
          "delta": 14,
          "absDelta": 14
        },
        {
          "driver": "HAD",
          "predicted": 23,
          "actual": 10,
          "delta": 13,
          "absDelta": 13
        },
        {
          "driver": "SAI",
          "predicted": 18,
          "actual": 8,
          "delta": 10,
          "absDelta": 10
        },
        {
          "driver": "LAW",
          "predicted": 22,
          "actual": 12,
          "delta": 10,
          "absDelta": 10
        }
      ]
    },
    {
      "season": 2025,
      "round": 6,
      "drivers_compared": 20,
      "mean_position_error": 6.6,
      "median_position_error": 6.0,
      "rmse_position_error": 7.867655305108378,
      "exact_matches": 1,
      "within_3": 5,
      "within_5": 9,
      "winner_hit": false,
      "podium_hits": 1,
      "mean_signed_delta": 6.3,
      "spearman_correlation": 0.6881181021789853,
      "ndcg_at_5": 0.7630176694161493,
      "biggest_misses": [
        {
          "driver": "TSU",
          "predicted": 27,
          "actual": 10,
          "delta": 17,
          "absDelta": 17
        },
        {
          "driver": "ANT",
          "predicted": 20,
          "actual": 6,
          "delta": 14,
          "absDelta": 14
        },
        {
          "driver": "ALB",
          "predicted": 17,
          "actual": 5,
          "delta": 12,
          "absDelta": 12
        },
        {
          "driver": "HAD",
          "predicted": 23,
          "actual": 11,
          "delta": 12,
          "absDelta": 12
        },
        {
          "driver": "PIA",
          "predicted": 10,
          "actual": 1,
          "delta": 9,
          "absDelta": 9
        }
      ]
    },
    {
      "season": 2025,
      "round": 7,
      "drivers_compared": 19,
      "mean_position_error": 6.368421052631579,
      "median_position_error": 6.0,
      "rmse_position_error": 7.3663530932705665,
      "exact_matches": 0,
      "within_3": 5,
      "within_5": 8,
      "winner_hit": false,
      "podium_hits": 2,
      "mean_signed_delta": 5.842105263157895,
      "spearman_correlation": 0.6874439407483748,
      "ndcg_at_5": 0.7031502153805566,
      "biggest_misses": [
        {
          "driver": "TSU",
          "predicted": 26,
          "actual": 10,
          "delta": 16,
          "absDelta": 16
        },
        {
          "driver": "HAD",
          "predicted": 21,
          "actual": 9,
          "delta": 12,
          "absDelta": 12
        },
        {
          "driver": "HAM",
          "predicted": 13,
          "actual": 4,
          "delta": 9,
          "absDelta": 9
        },
        {
          "driver": "ALB",
          "predicted": 14,
          "actual": 5,
          "delta": 9,
          "absDelta": 9
        },
        {
          "driver": "LAW",
          "predicted": 23,
          "actual": 14,
          "delta": 9,
          "absDelta": 9
        }
      ]
    },
    {
      "season": 2025,
      "round": 8,
      "drivers_compared": 20,
      "mean_position_error": 7.95,
      "median_position_error": 8.0,
      "rmse_position_error": 9.118662182579197,
      "exact_matches": 1,
      "within_3": 3,
      "within_5": 7,
      "winner_hit": false,
      "podium_hits": 0,
      "mean_signed_delta": 6.05,
      "spearman_correlation": 0.31041576507581864,
      "ndcg_at_5": 0.2231353605218925,
      "biggest_misses": [
        {
          "driver": "HAD",
          "predicted": 22,
          "actual": 6,
          "delta": 16,
          "absDelta": 16
        },
        {
          "driver": "LAW",
          "predicted": 24,
          "actual": 8,
          "delta": 16,
          "absDelta": 16
        },
        {
          "driver": "GAS",
          "predicted": 8,
          "actual": 20,
          "delta": -12,
          "absDelta": 12
        },
        {
          "driver": "NOR",
          "predicted": 13,
          "actual": 1,
          "delta": 12,
          "absDelta": 12
        },
        {
          "driver": "LEC",
          "predicted": 14,
          "actual": 2,
          "delta": 12,
          "absDelta": 12
        }
      ]
    },
    {
      "season": 2025,
      "round": 9,
      "drivers_compared": 19,
      "mean_position_error": 7.842105263157895,
      "median_position_error": 7.0,
      "rmse_position_error": 9.259419101934158,
      "exact_matches": 0,
      "within_3": 4,
      "within_5": 7,
      "winner_hit": false,
      "podium_hits": 1,
      "mean_signed_delta": 6.368421052631579,
      "spearman_correlation": 0.3019829659058749,
      "ndcg_at_5": 0.7034994661900285,
      "biggest_misses": [
        {
          "driver": "HUL",
          "predicted": 21,
          "actual": 5,
          "delta": 16,
          "absDelta": 16
        },
        {
          "driver": "HAD",
          "predicted": 22,
          "actual": 7,
          "delta": 15,
          "absDelta": 15
        },
        {
          "driver": "GAS",
          "predicted": 23,
          "actual": 8,
          "delta": 15,
          "absDelta": 15
        },
        {
          "driver": "LAW",
          "predicted": 25,
          "actual": 11,
          "delta": 14,
          "absDelta": 14
        },
        {
          "driver": "BOR",
          "predicted": 26,
          "actual": 12,
          "delta": 14,
          "absDelta": 14
        }
      ]
    },
    {
      "season": 2025,
      "round": 10,
      "drivers_compared": 20,
      "mean_position_error": 7.1,
      "median_position_error": 7.0,
      "rmse_position_error": 8.037412518964047,
      "exact_matches": 0,
      "within_3": 3,
      "within_5": 8,
      "winner_hit": false,
      "podium_hits": 1,
      "mean_signed_delta": 0.0,
      "spearman_correlation": 0.02857142857142857,
      "ndcg_at_5": 0.29205820897298396,
      "biggest_misses": [
        {
          "driver": "LAW",
          "predicted": 3,
          "actual": 19,
          "delta": -16,
          "absDelta": 16
        },
        {
          "driver": "HAD",
          "predicted": 2,
          "actual": 16,
          "delta": -14,
          "absDelta": 14
        },
        {
          "driver": "RUS",
          "predicted": 13,
          "actual": 1,
          "delta": 12,
          "absDelta": 12
        },
        {
          "driver": "ALO",
          "predicted": 18,
          "actual": 7,
          "delta": 11,
          "absDelta": 11
        },
        {
          "driver": "NOR",
          "predicted": 9,
          "actual": 18,
          "delta": -9,
          "absDelta": 9
        }
      ]
    },
    {
      "season": 2025,
      "round": 11,
      "drivers_compared": 20,
      "mean_position_error": 6.5,
      "median_position_error": 5.0,
      "rmse_position_error": 8.093207028119323,
      "exact_matches": 0,
      "within_3": 7,
      "within_5": 12,
      "winner_hit": false,
      "podium_hits": 1,
      "mean_signed_delta": 0.6,
      "spearman_correlation": 0.1941825694108278,
      "ndcg_at_5": 0.3071136896930767,
      "biggest_misses": [
        {
          "driver": "ANT",
          "predicted": 1,
          "actual": 19,
          "delta": -18,
          "absDelta": 18
        },
        {
          "driver": "OCO",
          "predicted": 25,
          "actual": 10,
          "delta": 15,
          "absDelta": 15
        },
        {
          "driver": "VER",
          "predicted": 4,
          "actual": 18,
          "delta": -14,
          "absDelta": 14
        },
        {
          "driver": "GAS",
          "predicted": 26,
          "actual": 13,
          "delta": 13,
          "absDelta": 13
        },
        {
          "driver": "ALO",
          "predicted": 16,
          "actual": 7,
          "delta": 9,
          "absDelta": 9
        }
      ]
    },
    {
      "season": 2025,
      "round": 12,
      "drivers_compared": 20,
      "mean_position_error": 8.2,
      "median_position_error": 8.0,
      "rmse_position_error": 9.726253132630262,
      "exact_matches": 1,
      "within_3": 5,
      "within_5": 7,
      "winner_hit": false,
      "podium_hits": 0,
      "mean_signed_delta": 0.0,
      "spearman_correlation": -0.42255639097744363,
      "ndcg_at_5": 0.0,
      "biggest_misses": [
        {
          "driver": "LAW",
          "predicted": 1,
          "actual": 19,
          "delta": -18,
          "absDelta": 18
        },
        {
          "driver": "BOR",
          "predicted": 2,
          "actual": 18,
          "delta": -16,
          "absDelta": 16
        },
        {
          "driver": "COL",
          "predicted": 5,
          "actual": 20,
          "delta": -15,
          "absDelta": 15
        },
        {
          "driver": "HAD",
          "predicted": 3,
          "actual": 17,
          "delta": -14,
          "absDelta": 14
        },
        {
          "driver": "VER",
          "predicted": 19,
          "actual": 5,
          "delta": 14,
          "absDelta": 14
        }
      ]
    },
    {
      "season": 2025,
      "round": 13,
      "drivers_compared": 20,
      "mean_position_error": 6.5,
      "median_position_error": 5.0,
      "rmse_position_error": 8.300602387778854,
      "exact_matches": 2,
      "within_3": 8,
      "within_5": 11,
      "winner_hit": false,
      "podium_hits": 0,
      "mean_signed_delta": 0.0,
      "spearman_correlation": -0.03609022556390978,
      "ndcg_at_5": 0.15064471735612164,
      "biggest_misses": [
        {
          "driver": "HAD",
          "predicted": 3,
          "actual": 20,
          "delta": -17,
          "absDelta": 17
        },
        {
          "driver": "COL",
          "predicted": 4,
          "actual": 19,
          "delta": -15,
          "absDelta": 15
        },
        {
          "driver": "VER",
          "predicted": 19,
          "actual": 4,
          "delta": 15,
          "absDelta": 15
        },
        {
          "driver": "LEC",
          "predicted": 15,
          "actual": 3,
          "delta": 12,
          "absDelta": 12
        },
        {
          "driver": "ALB",
          "predicted": 18,
          "actual": 6,
          "delta": 12,
          "absDelta": 12
        }
      ]
    },
    {
      "season": 2025,
      "round": 14,
      "drivers_compared": 20,
      "mean_position_error": 5.8,
      "median_position_error": 5.0,
      "rmse_position_error": 7.238784428341543,
      "exact_matches": 2,
      "within_3": 9,
      "within_5": 11,
      "winner_hit": true,
      "podium_hits": 2,
      "mean_signed_delta": 5.0,
      "spearman_correlation": 0.58796992481203,
      "ndcg_at_5": 0.930097254345091,
      "biggest_misses": [
        {
          "driver": "ANT",
          "predicted": 25,
          "actual": 10,
          "delta": 15,
          "absDelta": 15
        },
        {
          "driver": "VER",
          "predicted": 23,
          "actual": 9,
          "delta": 14,
          "absDelta": 14
        },
        {
          "driver": "BOR",
          "predicted": 17,
          "actual": 6,
          "delta": 11,
          "absDelta": 11
        },
        {
          "driver": "HAD",
          "predicted": 22,
          "actual": 11,
          "delta": 11,
          "absDelta": 11
        },
        {
          "driver": "SAI",
          "predicted": 24,
          "actual": 14,
          "delta": 10,
          "absDelta": 10
        }
      ]
    },
    {
      "season": 2025,
      "round": 15,
      "drivers_compared": 20,
      "mean_position_error": 6.4,
      "median_position_error": 4.0,
      "rmse_position_error": 8.294576541331088,
      "exact_matches": 2,
      "within_3": 8,
      "within_5": 11,
      "winner_hit": true,
      "podium_hits": 1,
      "mean_signed_delta": 0.0,
      "spearman_correlation": -0.03458646616541353,
      "ndcg_at_5": 0.7212634817761379,
      "biggest_misses": [
        {
          "driver": "HAD",
          "predicted": 20,
          "actual": 3,
          "delta": 17,
          "absDelta": 17
        },
        {
          "driver": "NOR",
          "predicted": 2,
          "actual": 18,
          "delta": -16,
          "absDelta": 16
        },
        {
          "driver": "LEC",
          "predicted": 3,
          "actual": 19,
          "delta": -16,
          "absDelta": 16
        },
        {
          "driver": "HAM",
          "predicted": 8,
          "actual": 20,
          "delta": -12,
          "absDelta": 12
        },
        {
          "driver": "BEA",
          "predicted": 18,
          "actual": 6,
          "delta": 12,
          "absDelta": 12
        }
      ]
    },
    {
      "season": 2025,
      "round": 16,
      "drivers_compared": 20,
      "mean_position_error": 4.9,
      "median_position_error": 5.0,
      "rmse_position_error": 5.822370651203855,
      "exact_matches": 1,
      "within_3": 9,
      "within_5": 11,
      "winner_hit": false,
      "podium_hits": 0,
      "mean_signed_delta": 0.0,
      "spearman_correlation": 0.49022556390977445,
      "ndcg_at_5": 0.08385508279837632,
      "biggest_misses": [
        {
          "driver": "ALB",
          "predicted": 20,
          "actual": 7,
          "delta": 13,
          "absDelta": 13
        },
        {
          "driver": "COL",
          "predicted": 8,
          "actual": 17,
          "delta": -9,
          "absDelta": 9
        },
        {
          "driver": "VER",
          "predicted": 10,
          "actual": 1,
          "delta": 9,
          "absDelta": 9
        },
        {
          "driver": "BOR",
          "predicted": 1,
          "actual": 8,
          "delta": -7,
          "absDelta": 7
        },
        {
          "driver": "ANT",
          "predicted": 2,
          "actual": 9,
          "delta": -7,
          "absDelta": 7
        }
      ]
    },
    {
      "season": 2025,
      "round": 17,
      "drivers_compared": 20,
      "mean_position_error": 5.4,
      "median_position_error": 5.0,
      "rmse_position_error": 6.557438524302,
      "exact_matches": 1,
      "within_3": 7,
      "within_5": 12,
      "winner_hit": false,
      "podium_hits": 0,
      "mean_signed_delta": 0.0,
      "spearman_correlation": 0.3533834586466165,
      "ndcg_at_5": 0.15064471735612164,
      "biggest_misses": [
        {
          "driver": "PIA",
          "predicted": 4,
          "actual": 20,
          "delta": -16,
          "absDelta": 16
        },
        {
          "driver": "SAI",
          "predicted": 14,
          "actual": 3,
          "delta": 11,
          "absDelta": 11
        },
        {
          "driver": "HUL",
          "predicted": 7,
          "actual": 16,
          "delta": -9,
          "absDelta": 9
        },
        {
          "driver": "TSU",
          "predicted": 15,
          "actual": 6,
          "delta": 9,
          "absDelta": 9
        },
        {
          "driver": "HAM",
          "predicted": 1,
          "actual": 8,
          "delta": -7,
          "absDelta": 7
        }
      ]
    },
    {
      "season": 2025,
      "round": 18,
      "drivers_compared": 20,
      "mean_position_error": 3.2,
      "median_position_error": 3.0,
      "rmse_position_error": 4.09878030638384,
      "exact_matches": 1,
      "within_3": 14,
      "within_5": 18,
      "winner_hit": false,
      "podium_hits": 0,
      "mean_signed_delta": 0.0,
      "spearman_correlation": 0.7473684210526316,
      "ndcg_at_5": 0.47113281420234215,
      "biggest_misses": [
        {
          "driver": "ALO",
          "predicted": 19,
          "actual": 7,
          "delta": 12,
          "absDelta": 12
        },
        {
          "driver": "HAM",
          "predicted": 2,
          "actual": 8,
          "delta": -6,
          "absDelta": 6
        },
        {
          "driver": "RUS",
          "predicted": 6,
          "actual": 1,
          "delta": 5,
          "absDelta": 5
        },
        {
          "driver": "LAW",
          "predicted": 10,
          "actual": 15,
          "delta": -5,
          "absDelta": 5
        },
        {
          "driver": "BEA",
          "predicted": 14,
          "actual": 9,
          "delta": 5,
          "absDelta": 5
        }
      ]
    },
    {
      "season": 2025,
      "round": 19,
      "drivers_compared": 20,
      "mean_position_error": 4.0,
      "median_position_error": 3.0,
      "rmse_position_error": 5.394441583704471,
      "exact_matches": 3,
      "within_3": 12,
      "within_5": 15,
      "winner_hit": false,
      "podium_hits": 1,
      "mean_signed_delta": 0.0,
      "spearman_correlation": 0.562406015037594,
      "ndcg_at_5": 0.5721765916141572,
      "biggest_misses": [
        {
          "driver": "SAI",
          "predicted": 8,
          "actual": 20,
          "delta": -12,
          "absDelta": 12
        },
        {
          "driver": "HUL",
          "predicted": 20,
          "actual": 8,
          "delta": 12,
          "absDelta": 12
        },
        {
          "driver": "ALO",
          "predicted": 19,
          "actual": 10,
          "delta": 9,
          "absDelta": 9
        },
        {
          "driver": "ANT",
          "predicted": 5,
          "actual": 13,
          "delta": -8,
          "absDelta": 8
        },
        {
          "driver": "HAD",
          "predicted": 9,
          "actual": 16,
          "delta": -7,
          "absDelta": 7
        }
      ]
    },
    {
      "season": 2025,
      "round": 20,
      "drivers_compared": 20,
      "mean_position_error": 4.1,
      "median_position_error": 4.0,
      "rmse_position_error": 5.039841267341661,
      "exact_matches": 2,
      "within_3": 10,
      "within_5": 14,
      "winner_hit": false,
      "podium_hits": 1,
      "mean_signed_delta": 0.0,
      "spearman_correlation": 0.6180451127819548,
      "ndcg_at_5": 0.6419033744922364,
      "biggest_misses": [
        {
          "driver": "LAW",
          "predicted": 10,
          "actual": 20,
          "delta": -10,
          "absDelta": 10
        },
        {
          "driver": "SAI",
          "predicted": 8,
          "actual": 17,
          "delta": -9,
          "absDelta": 9
        },
        {
          "driver": "OCO",
          "predicted": 17,
          "actual": 9,
          "delta": 8,
          "absDelta": 8
        },
        {
          "driver": "BOR",
          "predicted": 18,
          "actual": 10,
          "delta": 8,
          "absDelta": 8
        },
        {
          "driver": "BEA",
          "predicted": 11,
          "actual": 4,
          "delta": 7,
          "absDelta": 7
        }
      ]
    },
    {
      "season": 2025,
      "round": 21,
      "drivers_compared": 20,
      "mean_position_error": 4.9,
      "median_position_error": 4.0,
      "rmse_position_error": 6.395310782127793,
      "exact_matches": 2,
      "within_3": 9,
      "within_5": 13,
      "winner_hit": true,
      "podium_hits": 2,
      "mean_signed_delta": 0.0,
      "spearman_correlation": 0.3849624060150376,
      "ndcg_at_5": 0.8035633463980263,
      "biggest_misses": [
        {
          "driver": "LEC",
          "predicted": 5,
          "actual": 19,
          "delta": -14,
          "absDelta": 14
        },
        {
          "driver": "LAW",
          "predicted": 20,
          "actual": 7,
          "delta": 13,
          "absDelta": 13
        },
        {
          "driver": "HAM",
          "predicted": 7,
          "actual": 18,
          "delta": -11,
          "absDelta": 11
        },
        {
          "driver": "GAS",
          "predicted": 19,
          "actual": 10,
          "delta": 9,
          "absDelta": 9
        },
        {
          "driver": "HUL",
          "predicted": 17,
          "actual": 9,
          "delta": 8,
          "absDelta": 8
        }
      ]
    },
    {
      "season": 2025,
      "round": 22,
      "drivers_compared": 20,
      "mean_position_error": 5.7,
      "median_position_error": 4.0,
      "rmse_position_error": 7.758865896508329,
      "exact_matches": 2,
      "within_3": 9,
      "within_5": 12,
      "winner_hit": false,
      "podium_hits": 1,
      "mean_signed_delta": 0.0,
      "spearman_correlation": 0.09473684210526316,
      "ndcg_at_5": 0.4748238552898293,
      "biggest_misses": [
        {
          "driver": "NOR",
          "predicted": 1,
          "actual": 19,
          "delta": -18,
          "absDelta": 18
        },
        {
          "driver": "PIA",
          "predicted": 3,
          "actual": 20,
          "delta": -17,
          "absDelta": 17
        },
        {
          "driver": "LEC",
          "predicted": 20,
          "actual": 4,
          "delta": 16,
          "absDelta": 16
        },
        {
          "driver": "HAM",
          "predicted": 17,
          "actual": 8,
          "delta": 9,
          "absDelta": 9
        },
        {
          "driver": "STR",
          "predicted": 11,
          "actual": 18,
          "delta": -7,
          "absDelta": 7
        }
      ]
    },
    {
      "season": 2025,
      "round": 23,
      "drivers_compared": 20,
      "mean_position_error": 5.6,
      "median_position_error": 5.0,
      "rmse_position_error": 6.978538528947161,
      "exact_matches": 1,
      "within_3": 8,
      "within_5": 12,
      "winner_hit": false,
      "podium_hits": 1,
      "mean_signed_delta": 0.0,
      "spearman_correlation": 0.26766917293233083,
      "ndcg_at_5": 0.5587995754433605,
      "biggest_misses": [
        {
          "driver": "STR",
          "predicted": 1,
          "actual": 17,
          "delta": -16,
          "absDelta": 16
        },
        {
          "driver": "BEA",
          "predicted": 7,
          "actual": 19,
          "delta": -12,
          "absDelta": 12
        },
        {
          "driver": "LEC",
          "predicted": 19,
          "actual": 8,
          "delta": 11,
          "absDelta": 11
        },
        {
          "driver": "HAD",
          "predicted": 9,
          "actual": 18,
          "delta": -9,
          "absDelta": 9
        },
        {
          "driver": "LAW",
          "predicted": 18,
          "actual": 9,
          "delta": 9,
          "absDelta": 9
        }
      ]
    },
    {
      "season": 2025,
      "round": 24,
      "drivers_compared": 20,
      "mean_position_error": 5.0,
      "median_position_error": 5.0,
      "rmse_position_error": 6.340346993658944,
      "exact_matches": 1,
      "within_3": 8,
      "within_5": 13,
      "winner_hit": false,
      "podium_hits": 2,
      "mean_signed_delta": 0.0,
      "spearman_correlation": 0.3954887218045113,
      "ndcg_at_5": 0.6208529597763213,
      "biggest_misses": [
        {
          "driver": "LEC",
          "predicted": 19,
          "actual": 4,
          "delta": 15,
          "absDelta": 15
        },
        {
          "driver": "ANT",
          "predicted": 5,
          "actual": 15,
          "delta": -10,
          "absDelta": 10
        },
        {
          "driver": "HAM",
          "predicted": 18,
          "actual": 8,
          "delta": 10,
          "absDelta": 10
        },
        {
          "driver": "STR",
          "predicted": 1,
          "actual": 10,
          "delta": -9,
          "absDelta": 9
        },
        {
          "driver": "BOR",
          "predicted": 20,
          "actual": 11,
          "delta": 9,
          "absDelta": 9
        }
      ]
    }
  ],
  "summary": {
    "rounds_evaluated": 24,
    "season_mean_error": 6.272,
    "season_median_error": 5.0,
    "winner_hit_rate": 0.125,
    "podium_hit_rate": 0.306,
    "exact_match_rate": 0.051,
    "within_3_rate": 0.336,
    "within_5_rate": 0.515,
    "mean_spearman": 0.275,
    "mean_ndcg_at_5": 0.468
  }
}