{
  "round": 9,
  "season": 2026,
  "venueKey": "kansas-speedway",
  "venueName": "Kansas Speedway",
  "calibration": {
    "applied": true,
    "reason": "calibrated on 21 real round(s) of results"
  },
  "race": {
    "raceType": "race",
    "trackType": "intermediate",
    "markets": {
      "win": {
        "TYREDDICK": {
          "probability": 0.4,
          "rawProbability": 0.2132
        },
        "KYLARSON": {
          "probability": 0.0,
          "rawProbability": 0.024
        },
        "CHBRISCOE": {
          "probability": 0.0,
          "rawProbability": 0.0297
        },
        "DEHAMLIN": {
          "probability": 0.125,
          "rawProbability": 0.1278
        },
        "BUWALLACE": {
          "probability": 0.0,
          "rawProbability": 0.01
        },
        "BRKESELOWSKI": {
          "probability": 0.04,
          "rawProbability": 0.053
        },
        "WIBYRON": {
          "probability": 0.0,
          "rawProbability": 0.0253
        },
        "CHELLIOTT": {
          "probability": 0.04,
          "rawProbability": 0.0452
        },
        "TYGIBBS": {
          "probability": 0.125,
          "rawProbability": 0.1278
        },
        "CHBUESCHER": {
          "probability": 0.04,
          "rawProbability": 0.0385
        },
        "RYPREECE": {
          "probability": 0.04,
          "rawProbability": 0.0405
        },
        "AUCINDRIC": {
          "probability": 0.0,
          "rawProbability": 0.012
        },
        "CAHOCEVAR": {
          "probability": 0.0,
          "rawProbability": 0.0185
        },
        "RIHERBST": {
          "probability": 0.0,
          "rawProbability": 0.0022
        },
        "COHEIM": {
          "probability": 0.0,
          "rawProbability": 0.0008
        },
        "AUDILLON": {
          "probability": 0.0,
          "rawProbability": 0.0035
        },
        "TOGILLILAND": {
          "probability": 0.0,
          "rawProbability": 0.003
        },
        "ALBOWMAN": {
          "probability": 0.0,
          "rawProbability": 0.0005
        },
        "DASUAREZ": {
          "probability": 0.0,
          "rawProbability": 0.0208
        },
        "CHBELL": {
          "probability": 0.0,
          "rawProbability": 0.0262
        },
        "RISTENHOUSE": {
          "probability": 0.0,
          "rawProbability": 0.0013
        },
        "JONEMECHEK": {
          "probability": 0.0,
          "rawProbability": 0.001
        },
        "ERJONES": {
          "probability": 0.0,
          "rawProbability": 0.0092
        },
        "RYBLANEY": {
          "probability": 0.125,
          "rawProbability": 0.1045
        },
        "COCUSTER": {
          "probability": 0.0,
          "rawProbability": 0.0005
        },
        "ROCHASTAIN": {
          "probability": 0.0,
          "rawProbability": 0.0073
        },
        "JOBERRY": {
          "probability": 0.0,
          "rawProbability": 0.002
        },
        "NOGRAGSON": {
          "probability": 0.0,
          "rawProbability": 0.002
        },
        "COZILISCH": {
          "probability": 0.0,
          "rawProbability": 0.0008
        },
        "JOLOGANO": {
          "probability": 0.0,
          "rawProbability": 0.019
        },
        "AJALLMENDINGER": {
          "probability": 0.0,
          "rawProbability": 0.004
        },
        "ZASMITH": {
          "probability": 0.0,
          "rawProbability": 0.0032
        },
        "TYDILLON": {
          "probability": 0.0,
          "rawProbability": 0.0022
        },
        "MIMCDOWELL": {
          "probability": 0.0,
          "rawProbability": 0.0083
        },
        "KYBUSCH": {
          "probability": 0.0,
          "rawProbability": 0.0025
        },
        "SHGISBERGEN": {
          "probability": 0.0,
          "rawProbability": 0.0097
        },
        "COWARE": {
          "probability": 0.0,
          "rawProbability": 0.0
        }
      },
      "podium": {
        "TYREDDICK": {
          "probability": 0.5833,
          "rawProbability": 0.5278
        },
        "KYLARSON": {
          "probability": 0.1296,
          "rawProbability": 0.086
        },
        "CHBRISCOE": {
          "probability": 0.1296,
          "rawProbability": 0.0922
        },
        "DEHAMLIN": {
          "probability": 0.25,
          "rawProbability": 0.3725
        },
        "BUWALLACE": {
          "probability": 0.0513,
          "rawProbability": 0.035
        },
        "BRKESELOWSKI": {
          "probability": 0.15,
          "rawProbability": 0.1862
        },
        "WIBYRON": {
          "probability": 0.1296,
          "rawProbability": 0.0955
        },
        "CHELLIOTT": {
          "probability": 0.1296,
          "rawProbability": 0.1502
        },
        "TYGIBBS": {
          "probability": 0.25,
          "rawProbability": 0.373
        },
        "CHBUESCHER": {
          "probability": 0.1296,
          "rawProbability": 0.1303
        },
        "RYPREECE": {
          "probability": 0.1296,
          "rawProbability": 0.126
        },
        "AUCINDRIC": {
          "probability": 0.0513,
          "rawProbability": 0.0307
        },
        "CAHOCEVAR": {
          "probability": 0.0909,
          "rawProbability": 0.068
        },
        "RIHERBST": {
          "probability": 0.0,
          "rawProbability": 0.006
        },
        "COHEIM": {
          "probability": 0.0,
          "rawProbability": 0.0043
        },
        "AUDILLON": {
          "probability": 0.0,
          "rawProbability": 0.0115
        },
        "TOGILLILAND": {
          "probability": 0.0,
          "rawProbability": 0.0105
        },
        "ALBOWMAN": {
          "probability": 0.0,
          "rawProbability": 0.0025
        },
        "DASUAREZ": {
          "probability": 0.0909,
          "rawProbability": 0.0655
        },
        "CHBELL": {
          "probability": 0.1296,
          "rawProbability": 0.092
        },
        "RISTENHOUSE": {
          "probability": 0.0,
          "rawProbability": 0.0055
        },
        "JONEMECHEK": {
          "probability": 0.0,
          "rawProbability": 0.006
        },
        "ERJONES": {
          "probability": 0.0513,
          "rawProbability": 0.028
        },
        "RYBLANEY": {
          "probability": 0.15,
          "rawProbability": 0.306
        },
        "COCUSTER": {
          "probability": 0.0,
          "rawProbability": 0.0027
        },
        "ROCHASTAIN": {
          "probability": 0.0417,
          "rawProbability": 0.0238
        },
        "JOBERRY": {
          "probability": 0.0,
          "rawProbability": 0.0067
        },
        "NOGRAGSON": {
          "probability": 0.0,
          "rawProbability": 0.005
        },
        "COZILISCH": {
          "probability": 0.0,
          "rawProbability": 0.0057
        },
        "JOLOGANO": {
          "probability": 0.0909,
          "rawProbability": 0.055
        },
        "AJALLMENDINGER": {
          "probability": 0.0,
          "rawProbability": 0.0127
        },
        "ZASMITH": {
          "probability": 0.0,
          "rawProbability": 0.0125
        },
        "TYDILLON": {
          "probability": 0.0,
          "rawProbability": 0.0047
        },
        "MIMCDOWELL": {
          "probability": 0.0417,
          "rawProbability": 0.024
        },
        "KYBUSCH": {
          "probability": 0.0,
          "rawProbability": 0.008
        },
        "SHGISBERGEN": {
          "probability": 0.0513,
          "rawProbability": 0.0272
        },
        "COWARE": {
          "probability": 0.0,
          "rawProbability": 0.0005
        }
      },
      "top6": {
        "TYREDDICK": {
          "probability": 0.8462,
          "rawProbability": 0.7895
        },
        "KYLARSON": {
          "probability": 0.2737,
          "rawProbability": 0.2112
        },
        "CHBRISCOE": {
          "probability": 0.2737,
          "rawProbability": 0.2157
        },
        "DEHAMLIN": {
          "probability": 0.8462,
          "rawProbability": 0.6518
        },
        "BUWALLACE": {
          "probability": 0.1316,
          "rawProbability": 0.09
        },
        "BRKESELOWSKI": {
          "probability": 0.2737,
          "rawProbability": 0.396
        },
        "WIBYRON": {
          "probability": 0.2737,
          "rawProbability": 0.21
        },
        "CHELLIOTT": {
          "probability": 0.2737,
          "rawProbability": 0.3367
        },
        "TYGIBBS": {
          "probability": 0.5,
          "rawProbability": 0.6408
        },
        "CHBUESCHER": {
          "probability": 0.2737,
          "rawProbability": 0.3167
        },
        "RYPREECE": {
          "probability": 0.2737,
          "rawProbability": 0.2823
        },
        "AUCINDRIC": {
          "probability": 0.1316,
          "rawProbability": 0.0813
        },
        "CAHOCEVAR": {
          "probability": 0.2737,
          "rawProbability": 0.1762
        },
        "RIHERBST": {
          "probability": 0.0133,
          "rawProbability": 0.0158
        },
        "COHEIM": {
          "probability": 0.0133,
          "rawProbability": 0.0115
        },
        "AUDILLON": {
          "probability": 0.0133,
          "rawProbability": 0.03
        },
        "TOGILLILAND": {
          "probability": 0.0133,
          "rawProbability": 0.0288
        },
        "ALBOWMAN": {
          "probability": 0.0,
          "rawProbability": 0.0055
        },
        "DASUAREZ": {
          "probability": 0.1316,
          "rawProbability": 0.1537
        },
        "CHBELL": {
          "probability": 0.2737,
          "rawProbability": 0.2125
        },
        "RISTENHOUSE": {
          "probability": 0.0133,
          "rawProbability": 0.0147
        },
        "JONEMECHEK": {
          "probability": 0.0133,
          "rawProbability": 0.0145
        },
        "ERJONES": {
          "probability": 0.1316,
          "rawProbability": 0.0707
        },
        "RYBLANEY": {
          "probability": 0.2737,
          "rawProbability": 0.567
        },
        "COCUSTER": {
          "probability": 0.0,
          "rawProbability": 0.0057
        },
        "ROCHASTAIN": {
          "probability": 0.1316,
          "rawProbability": 0.061
        },
        "JOBERRY": {
          "probability": 0.0133,
          "rawProbability": 0.0173
        },
        "NOGRAGSON": {
          "probability": 0.0133,
          "rawProbability": 0.0147
        },
        "COZILISCH": {
          "probability": 0.0133,
          "rawProbability": 0.015
        },
        "JOLOGANO": {
          "probability": 0.1316,
          "rawProbability": 0.1363
        },
        "AJALLMENDINGER": {
          "probability": 0.0133,
          "rawProbability": 0.0323
        },
        "ZASMITH": {
          "probability": 0.0133,
          "rawProbability": 0.0365
        },
        "TYDILLON": {
          "probability": 0.0,
          "rawProbability": 0.0092
        },
        "MIMCDOWELL": {
          "probability": 0.1316,
          "rawProbability": 0.0635
        },
        "KYBUSCH": {
          "probability": 0.0133,
          "rawProbability": 0.0267
        },
        "SHGISBERGEN": {
          "probability": 0.0732,
          "rawProbability": 0.0573
        },
        "COWARE": {
          "probability": 0.0,
          "rawProbability": 0.0015
        }
      },
      "top10": {
        "TYREDDICK": {
          "probability": 0.8333,
          "rawProbability": 0.89
        },
        "KYLARSON": {
          "probability": 0.4412,
          "rawProbability": 0.424
        },
        "CHBRISCOE": {
          "probability": 0.4412,
          "rawProbability": 0.428
        },
        "DEHAMLIN": {
          "probability": 0.8333,
          "rawProbability": 0.8323
        },
        "BUWALLACE": {
          "probability": 0.25,
          "rawProbability": 0.2112
        },
        "BRKESELOWSKI": {
          "probability": 0.5714,
          "rawProbability": 0.649
        },
        "WIBYRON": {
          "probability": 0.4412,
          "rawProbability": 0.4243
        },
        "CHELLIOTT": {
          "probability": 0.5714,
          "rawProbability": 0.608
        },
        "TYGIBBS": {
          "probability": 0.8333,
          "rawProbability": 0.822
        },
        "CHBUESCHER": {
          "probability": 0.5714,
          "rawProbability": 0.5817
        },
        "RYPREECE": {
          "probability": 0.4412,
          "rawProbability": 0.5525
        },
        "AUCINDRIC": {
          "probability": 0.2222,
          "rawProbability": 0.1895
        },
        "CAHOCEVAR": {
          "probability": 0.4348,
          "rawProbability": 0.3663
        },
        "RIHERBST": {
          "probability": 0.0448,
          "rawProbability": 0.0367
        },
        "COHEIM": {
          "probability": 0.0448,
          "rawProbability": 0.0267
        },
        "AUDILLON": {
          "probability": 0.0448,
          "rawProbability": 0.0745
        },
        "TOGILLILAND": {
          "probability": 0.0833,
          "rawProbability": 0.0775
        },
        "ALBOWMAN": {
          "probability": 0.0,
          "rawProbability": 0.0125
        },
        "DASUAREZ": {
          "probability": 0.35,
          "rawProbability": 0.3038
        },
        "CHBELL": {
          "probability": 0.4412,
          "rawProbability": 0.4293
        },
        "RISTENHOUSE": {
          "probability": 0.0448,
          "rawProbability": 0.0325
        },
        "JONEMECHEK": {
          "probability": 0.0448,
          "rawProbability": 0.035
        },
        "ERJONES": {
          "probability": 0.2222,
          "rawProbability": 0.1557
        },
        "RYBLANEY": {
          "probability": 0.5714,
          "rawProbability": 0.773
        },
        "COCUSTER": {
          "probability": 0.0,
          "rawProbability": 0.0145
        },
        "ROCHASTAIN": {
          "probability": 0.2,
          "rawProbability": 0.1403
        },
        "JOBERRY": {
          "probability": 0.0448,
          "rawProbability": 0.0385
        },
        "NOGRAGSON": {
          "probability": 0.0448,
          "rawProbability": 0.0338
        },
        "COZILISCH": {
          "probability": 0.0448,
          "rawProbability": 0.0343
        },
        "JOLOGANO": {
          "probability": 0.35,
          "rawProbability": 0.2895
        },
        "AJALLMENDINGER": {
          "probability": 0.0448,
          "rawProbability": 0.0722
        },
        "ZASMITH": {
          "probability": 0.0833,
          "rawProbability": 0.0818
        },
        "TYDILLON": {
          "probability": 0.0,
          "rawProbability": 0.0187
        },
        "MIMCDOWELL": {
          "probability": 0.2,
          "rawProbability": 0.139
        },
        "KYBUSCH": {
          "probability": 0.0448,
          "rawProbability": 0.0648
        },
        "SHGISBERGEN": {
          "probability": 0.1304,
          "rawProbability": 0.1293
        },
        "COWARE": {
          "probability": 0.0,
          "rawProbability": 0.0075
        }
      }
    },
    "dnf": {
      "TYREDDICK": 0.0915,
      "KYLARSON": 0.1079,
      "CHBRISCOE": 0.1324,
      "DEHAMLIN": 0.1169,
      "BUWALLACE": 0.1651,
      "BRKESELOWSKI": 0.1406,
      "WIBYRON": 0.1242,
      "CHELLIOTT": 0.0997,
      "TYGIBBS": 0.1242,
      "CHBUESCHER": 0.0915,
      "RYPREECE": 0.1079,
      "AUCINDRIC": 0.1242,
      "CAHOCEVAR": 0.1488,
      "RIHERBST": 0.1324,
      "COHEIM": 0.1593,
      "AUDILLON": 0.1242,
      "TOGILLILAND": 0.1161,
      "ALBOWMAN": 0.1373,
      "DASUAREZ": 0.1651,
      "CHBELL": 0.1161,
      "RISTENHOUSE": 0.1161,
      "JONEMECHEK": 0.1161,
      "ERJONES": 0.1161,
      "RYBLANEY": 0.157,
      "COCUSTER": 0.1242,
      "ROCHASTAIN": 0.1161,
      "JOBERRY": 0.1651,
      "NOGRAGSON": 0.1488,
      "COZILISCH": 0.1746,
      "JOLOGANO": 0.1242,
      "AJALLMENDINGER": 0.1406,
      "ZASMITH": 0.1324,
      "TYDILLON": 0.1161,
      "MIMCDOWELL": 0.0997,
      "KYBUSCH": 0.1079,
      "SHGISBERGEN": 0.1161,
      "COWARE": 0.1733
    },
    "h2h": {
      "TYREDDICK": {
        "DEHAMLIN": 0.6015,
        "TYGIBBS": 0.6108,
        "RYBLANEY": 0.647,
        "CHELLIOTT": 0.757,
        "CHBUESCHER": 0.7722,
        "BRKESELOWSKI": 0.7408,
        "RYPREECE": 0.79,
        "KYLARSON": 0.8187,
        "CHBELL": 0.8183,
        "WIBYRON": 0.8197,
        "CHBRISCOE": 0.8227
      },
      "DEHAMLIN": {
        "TYREDDICK": 0.3985,
        "TYGIBBS": 0.508,
        "RYBLANEY": 0.5567,
        "CHELLIOTT": 0.6847,
        "CHBUESCHER": 0.7035,
        "BRKESELOWSKI": 0.656,
        "RYPREECE": 0.712,
        "KYLARSON": 0.761,
        "CHBELL": 0.75,
        "WIBYRON": 0.7612,
        "CHBRISCOE": 0.7572
      },
      "TYGIBBS": {
        "TYREDDICK": 0.3892,
        "DEHAMLIN": 0.492,
        "RYBLANEY": 0.553,
        "CHELLIOTT": 0.6765,
        "CHBUESCHER": 0.6853,
        "BRKESELOWSKI": 0.654,
        "RYPREECE": 0.7105,
        "KYLARSON": 0.7485,
        "CHBELL": 0.744,
        "WIBYRON": 0.752,
        "CHBRISCOE": 0.7472
      },
      "RYBLANEY": {
        "TYREDDICK": 0.353,
        "DEHAMLIN": 0.4432,
        "TYGIBBS": 0.447,
        "CHELLIOTT": 0.6292,
        "CHBUESCHER": 0.6442,
        "BRKESELOWSKI": 0.6025,
        "RYPREECE": 0.654,
        "KYLARSON": 0.7147,
        "CHBELL": 0.7125,
        "WIBYRON": 0.7183,
        "CHBRISCOE": 0.7033
      },
      "CHELLIOTT": {
        "TYREDDICK": 0.243,
        "DEHAMLIN": 0.3152,
        "TYGIBBS": 0.3235,
        "RYBLANEY": 0.3708,
        "CHBUESCHER": 0.5165,
        "BRKESELOWSKI": 0.468,
        "RYPREECE": 0.5275,
        "KYLARSON": 0.6098,
        "CHBELL": 0.6122,
        "WIBYRON": 0.6082,
        "CHBRISCOE": 0.613
      },
      "CHBUESCHER": {
        "TYREDDICK": 0.2278,
        "DEHAMLIN": 0.2965,
        "TYGIBBS": 0.3147,
        "RYBLANEY": 0.3558,
        "CHELLIOTT": 0.4835,
        "BRKESELOWSKI": 0.4575,
        "RYPREECE": 0.5245,
        "KYLARSON": 0.6,
        "CHBELL": 0.602,
        "WIBYRON": 0.596,
        "CHBRISCOE": 0.5975
      },
      "BRKESELOWSKI": {
        "TYREDDICK": 0.2592,
        "DEHAMLIN": 0.344,
        "TYGIBBS": 0.346,
        "RYBLANEY": 0.3975,
        "CHELLIOTT": 0.532,
        "CHBUESCHER": 0.5425,
        "RYPREECE": 0.5687,
        "KYLARSON": 0.6338,
        "CHBELL": 0.6248,
        "WIBYRON": 0.6248,
        "CHBRISCOE": 0.6235
      },
      "RYPREECE": {
        "TYREDDICK": 0.21,
        "DEHAMLIN": 0.288,
        "TYGIBBS": 0.2895,
        "RYBLANEY": 0.346,
        "CHELLIOTT": 0.4725,
        "CHBUESCHER": 0.4755,
        "BRKESELOWSKI": 0.4313,
        "KYLARSON": 0.582,
        "CHBELL": 0.57,
        "WIBYRON": 0.579,
        "CHBRISCOE": 0.5737
      },
      "KYLARSON": {
        "TYREDDICK": 0.1812,
        "DEHAMLIN": 0.239,
        "TYGIBBS": 0.2515,
        "RYBLANEY": 0.2853,
        "CHELLIOTT": 0.3902,
        "CHBUESCHER": 0.4,
        "BRKESELOWSKI": 0.3663,
        "RYPREECE": 0.418,
        "CHBELL": 0.4928,
        "WIBYRON": 0.4988,
        "CHBRISCOE": 0.4963
      },
      "CHBELL": {
        "TYREDDICK": 0.1817,
        "DEHAMLIN": 0.25,
        "TYGIBBS": 0.256,
        "RYBLANEY": 0.2875,
        "CHELLIOTT": 0.3877,
        "CHBUESCHER": 0.398,
        "BRKESELOWSKI": 0.3752,
        "RYPREECE": 0.43,
        "KYLARSON": 0.5072,
        "WIBYRON": 0.5092,
        "CHBRISCOE": 0.499
      },
      "WIBYRON": {
        "TYREDDICK": 0.1802,
        "DEHAMLIN": 0.2387,
        "TYGIBBS": 0.248,
        "RYBLANEY": 0.2818,
        "CHELLIOTT": 0.3917,
        "CHBUESCHER": 0.404,
        "BRKESELOWSKI": 0.3752,
        "RYPREECE": 0.421,
        "KYLARSON": 0.5012,
        "CHBELL": 0.4908,
        "CHBRISCOE": 0.5
      },
      "CHBRISCOE": {
        "TYREDDICK": 0.1772,
        "DEHAMLIN": 0.2427,
        "TYGIBBS": 0.2527,
        "RYBLANEY": 0.2968,
        "CHELLIOTT": 0.387,
        "CHBUESCHER": 0.4025,
        "BRKESELOWSKI": 0.3765,
        "RYPREECE": 0.4263,
        "KYLARSON": 0.5038,
        "CHBELL": 0.501,
        "WIBYRON": 0.5
      }
    },
    "method": "monte-carlo-dnf-composed",
    "monteCarloSamples": 4000,
    "temperature": 0.5
  }
}
